Workbook

Sheet Guide
A1: PIADE Packaging OEE - Lean Six Sigma DMAIC Workbook
A2: Data: PIADE (Kaggle) 5 packaging machines, 429,394 state intervals, Jan 2020 - Dec 2021. Heavy lifting in PostgreSQL (sql/ folder); this workbook = analysis + decisions.
A4: Phase | B4: Question it answers | C4: Tabs in this workbook | D4: PostgreSQL views | E4: Tools used | F4: Tollgate deliverable
A5: DEFINE | B5: What problem, for whom, how big, what goal? | C5: D1_Charter, D2_SIPOC, D3_VOC_CTQ | D5: v_oee_summary (baseline) | E5: Project charter, SIPOC, VOC->CTQ tree | F5: Signed charter with SMART goal
A6: MEASURE | B6: How good is the process today, and can we trust the data? | C6: Inputs, M1_DataQuality, M2_OEE, M3_LossTree, M4_Pareto, M5_Reliability, M6_Sigma | D6: v_data_quality, v_daily_machine, v_oee_summary, v_loss_tree, v_pareto_alarm, v_reliability | E6: Data collection plan, MSA (integrity checks), OEE, loss tree, Pareto, MTBF/MTTR, DPMO/sigma | F6: Validated baseline: OEE 51.7%, loss tree, vital few
A7: ANALYZE | B7: Which causes actually drive the losses? | C7: A1_RCA, A2_FMEA, A3_Hypothesis | D7: v_shift_state_share, v_alarm_shift_crosstab, v_fmea_inputs, v_hourly_profile | E7: Fishbone (6M), 5 Whys, data-driven FMEA, ANOVA, Welch t, chi-square, regression | F7: Verified root causes (data vs hypothesis)
A8: IMPROVE | B8: What do we change, and what is it worth? | C8: I1_Solutions, I2_OEE_Scenario, I3_SMED, I4_PokaYoke, I5_5S_Audit, I6_Kaizen, I7_Kanban, I8_Inventory | D8: v_smed_baseline, v_kanban, v_material_demand, v_inventory_policy | E8: Solution matrix, SMED, Poka-Yoke, 5S, Kaizen/PDCA, Kanban, VSM future state, SS/ROP/EOQ | F8: Prioritised plan + projected OEE bridge
A9: CONTROL | B9: How do we hold the gain? | C9: C1_XbarR_s1, C2_Capability, C3_ControlPlan, C4_OCAP | D9: v_xbar_r_subgroups, v_xbar_r_limits, v_xbar_r_chart, v_capability | E9: X-bar & R chart, Cpk/Ppk, control plan, OCAP, Power BI cockpit | F9: Control plan handed to process owner
A11: Colour code
A12: 1234 | B12: Blue text = hard-coded input / SQL extract value
A13: =1+1 -> 2 | B13: Black text = formula on this sheet
A14: =Inputs!B5 -> 0.65 | B14: Green text = formula linking another sheet
A15: 0.65 | B15: Yellow fill = assumption / cell you may edit (everything recalculates)
A17: Refresh cycle | B17: 1) run sql/01 + sql/02 in PostgreSQL 2) run sql/03_export.sql 3) paste the CSVs into the Data_* tabs 4) all tabs recalculate

Sheet Inputs
A1: Inputs & assumptions (edit yellow cells only)
A2: Every hard-coded assumption lives here and is referenced by formulas elsewhere.
A4: Parameter | B4: Value | C4: Unit | D4: Source / note
A5: OEE target (project goal) | B5: 0.65 | C5: fraction | D5: Project goal; world-class benchmark is 0.85
A6: Quality LSL (daily good / total) | B6: 0.99 | C6: fraction | D6: Assumed customer requirement
A7: Contribution per good pack | B7: 0.6 | C7: INR | D7: ASSUMPTION - replace with finance data
A8: Study period | B8: 2 | C8: years | D8: Jan 2020 - Dec 2021 (731 days)
A9: Packaging blank unit cost | B9: 4 | C9: INR | D9: ASSUMPTION
A10: Ordering cost per PO | B10: 6000 | C10: INR | D10: ASSUMPTION
A11: Annual holding rate | B11: 0.24 | C11: fraction | D11: ASSUMPTION (capital + storage + obsolescence)
A12: Supplier lead time | B12: 7 | C12: days | D12: ASSUMPTION
A13: Lead-time standard deviation | B13: 1.5 | C13: days | D13: ASSUMPTION
A14: Target cycle service level | B14: 0.98 | C14: fraction | D14: Policy choice
A15: Kanban container quantity | B15: 2000 | C15: blanks/bin | D15: ASSUMPTION
A16: Kanban replenishment lead time | B16: 8 | C16: hours | D16: ASSUMPTION (one shift)
... A23: Spare-kit holding rate | B23: 0.2 | C23: fraction | D23: ASSUMPTION

Sheet D1_Charter
A1: D1 - Project charter
A2: DEFINE. Baseline numbers are live formulas from the Measure tabs.
A4: Element | B4: Content
A5: Project title | B5: Raise OEE of the packaging-machine fleet (PIADE s_1..s_5) through Lean Six Sigma
A6: Problem statement | B6: ="Between Jan-2020 and Dec-2021 the 5 packaging machines ran at a fleet OEE of "&TEXT(M2_OEE!O10,"0.0%")&" against a "&TEXT(Inputs!B5,"0%")&" target. "&TEXT(M2_OEE!G10/M2_OEE!D10,"0%")&" of planned time was idle with no reason code and "&TEXT(M2_OEE!F10/M2_OEE!D10,"0.0%")&" was lost to "&TEXT(M5_Reliability!B10,"#,##0")&" alarm stops. s_1, the highest-volume machine, is the only one whose OEE fell in 2021." -> Between Jan-2020 and Dec-2021 the 5 packaging machines ran at a fleet OEE of 51.7% against a 65% target. 27% of planned time was idle with no reason code and 8.4% was lost to 92,005 alarm stops. s_1, the highest-volume machine, is the only one whose OEE fell in 2021.
A7: Business case | B7: ="Every OEE point is worth ~"&TEXT(M2_OEE!D10/Inputs!B8*M2_OEE!I10/M2_OEE!E10*0.01,"#,##0")&" good packs/year (~INR "&TEXT(M2_OEE!D10/Inputs!B8*M2_OEE!I10/M2_OEE!E10*0.01*Inputs!B7/100000,"0.0")&" lakh contribution at the assumed margin)." -> Every OEE point is worth ~919,720 good packs/year (~INR 5.5 lakh contribution at the assumed margin).
A8: Goal (SMART) | B8: ="Raise fleet OEE from "&TEXT(M2_OEE!O10,"0.0%")&" to >= 60% (stretch "&TEXT(Inputs!B5,"0%")&") within 6 months of go-live, while holding quality >= 99.5% and packaging-material service level >= 98%." -> Raise fleet OEE from 51.7% to >= 60% (stretch 65%) within 6 months of go-live, while holding quality >= 99.5% and packaging-material service level >= 98%.
A9: Primary metric (Y) | B9: OEE = Availability x Performance x Quality (TPM definition; idle counts as availability loss)
A10: Secondary metrics | B10: Alarm downtime hours (vital-few codes), idle share by shift, changeover minutes, material stock-outs, safety-stock value
A11: In scope | B11: Machines s_1..s_5; alarm stops, idle, speed loss, changeovers; line-side packaging-material supply
A12: Out of scope | B12: Upstream filling / downstream palletising; capex machine redesign; product-mix planning
A13: Pilot | B13: s_1 (33% of fleet volume, largest single loss A_065, only machine that degraded in 2021)
A14: Team (fill in) | B14: Sponsor: Plant head | Champion: Packaging manager | Black/Green Belt: <you> | Members: shift leads, maintenance, stores, quality
A15: Timeline | B15: Define wk 1-2 | Measure wk 3-5 | Analyze wk 6-8 | Improve wk 9-16 (pilot s_1) | Control wk 17-24
A16: Honesty note | B16: Retrospective study on a public dataset: Improve results are PROJECTIONS using assumed reduction rates, not measured outcomes.

Sheet D2_SIPOC
A1: D2 - SIPOC
A2: DEFINE. High-level map of the packaging process.
A4: Suppliers | B4: Inputs | C4: Process (high level) | D4: Outputs | E4: Customers
A5: Film / carton suppliers | B5: Carton blanks, film, glue | C5: 1. Receive & store packaging material | D5: Packed units (po) | E5: Distribution centre
A6: Upstream filling line | B6: Product units to pack (pi) | C6: 2. Stage material line-side (Kanban) | D6: Rejects (pi - po) | E6: Sales / key accounts
A7: Maintenance | B7: Machine availability, spares | C7: 3. Changeover / set-up (SMED) | D7: Alarm & state logs | E7: Quality / QA
A8: Planning (S&OP) | B8: Schedule, set speed | C8: 4. Run & pack at rated speed | D8: OEE, downtime data | E8: Plant management
A9: Operators (3 shifts) | B9: Skills, standard work | C9: 5. Stop recovery / restart | D9: Changeover records | E9: Finance (COPQ)
A10: IT / MES | B10: State + counter logging | C10: 6. Record, review, improve | D10: Dashboards | E10: Continuous-improvement team

Sheet D3_VOC_CTQ
A1: D3 - Voice of customer -> CTQ tree
A2: DEFINE. Translate vague needs into measurable CTQs with specs.
A4: Voice of customer / business | B4: Driver | C4: CTQ (measurable) | D4: Operational definition | E4: Target / spec | F4: Baseline (live)
A5: 'We never ship full orders on time' | B5: Capacity | C5: OEE (fleet) | D5: Run/PPT x Output/Ideal x Good/Output | E5: ="LSL "&TEXT(Inputs!B5,"0%") -> LSL 65% | F5: =M2_OEE!O10 -> 0.51736506
A6: 'The line keeps stopping' | B6: Availability | C6: Alarm downtime share | D6: Downtime h / planned h | E6: <= 6% | F6: =M2_OEE!F10/M2_OEE!D10 -> 0.083716532
A7: 'Nobody is at the machine at night' | B7: Availability | C7: Idle share | D7: Idle h / planned h | E7: <= 20% | F7: =M2_OEE!G10/M2_OEE!D10 -> 0.27305744
A8: 'It runs slow' | B8: Performance | C8: Performance rate | D8: Units in / ideal units at rated speed | E8: >= 88% | F8: =M2_OEE!M10 -> 0.80763044
A9: 'Too many damaged packs' | B9: Quality | C9: Quality rate | D9: Units out / units in | E9: =">= "&TEXT(Inputs!B6,"0.0%") -> >= 99.0% | F9: =M2_OEE!N10 -> 0.99591163
A10: 'Changeovers take forever' | B10: Flexibility | C10: Mean changeover minutes | D10: Planned stop 10 min - 4 h | E10: -40% vs baseline | F10: =I3_SMED!C10 -> 51.368459
A11: 'We run out of cartons' | B11: Supply | C11: Cycle service level | D11: Order cycles without stock-out | E11: =">= "&TEXT(Inputs!B14,"0%") -> >= 98% | F11: see I8_Inventory

Sheet M1_DataQuality
A1: M1 - Data collection plan & data integrity (MSA substitute)
A2: MEASURE. Machine logs cannot be re-measured, so a Gage R&R is replaced by integrity checks (results from v_data_quality).
A4: Integrity check | B4: Result | C4: Interpretation
A5: rows loaded | B5: 429394 | C5: Complete load
A6: null cells in key columns | B6: 0 | C6: OK
A7: duplicate rows | B7: 0 | C7: OK
A8: elapsed vs (end-start) mismatch > 1 % | B8: 0 | C8: OK
A9: negative counter deltas (pi) | B9: 85 | C9: Counter resets -> excluded
A10: counter deltas rejected as glitch | B10: 2397 | C10: Counter delta > 3x theoretical -> excluded (0.6%)
A11: alarm on non-downtime row | B11: 0 | C11: OK
A12: downtime row without alarm | B12: 0 | C12: OK
A13: idle rows with a reason code | B13: 0 | C13: GAP: idle is never explained -> Control-phase fix
A16: Metric | B16: Operational definition | C16: Source field(s) | D16: SQL view | E16: Frequency | F16: Unit
A17: Planned production time | B17: Logged time minus scheduled_downtime | C17: type, elapsed (ms) | D17: v_daily_machine | E17: Daily / shift | F17: h
A18: Run time | B18: Time in production + performance_loss | C18: type, elapsed | D18: v_daily_machine | E18: Daily / shift | F18: h
A19: Units in / out | B19: Delta of cumulative counters pi / po (read at interval end) | C19: pi, po | D19: f_interval (LAG) | E19: Per interval | F19: packs
A20: Ideal units | B20: Rated speed x run time | C20: speed, elapsed | D20: v_daily_machine | E20: Daily | F20: packs
A21: Stop event | B21: Consecutive downtime rows, same alarm, same machine | C21: alarm, type | D21: f_downtime_event | E21: Per event | F21: count, min
A22: Shift | B22: A 06-14, B 14-22, C 22-06 (UTC, assumed) | C22: interval_start | D22: f_interval | E22: Per interval | F22: -
A23: Production day | B23: 06:00 to 06:00 (keeps a night shift in one day) | C23: interval_start | D23: f_interval | E23: Per interval | F23: date

Sheet M2_OEE
A1: M2 - Baseline OEE by machine
A2: MEASURE. SUMIF over Data_Daily (SQL extract of v_daily_machine). OEE = A x P x Q.
A4: Machine | B4: Logged h | C4: Scheduled h | D4: Planned h | E4: Run h | F4: Alarm downtime h | G4: Idle h | H4: Perf-loss state h | I4: Ideal units | J4: Units in | K4: Units out | L4: Availability | M4: Performance | N4: Quality | O4: OEE | P4: Gap to target (pts) | Q4: Utilization (run/logged)
A5: s_1 | B5: =SUMIF(Data_Daily!$A$2:$A$2407,$A5,Data_Daily!$C$2:$C$2407)/3600 -> 13458.096 | C5: =SUMIF(Data_Daily!$A$2:$A$2407,$A5,Data_Daily!$D$2:$D$2407)/3600 -> 1552.0647 | D5: =SUMIF(Data_Daily!$A$2:$A$2407,$A5,Data_Daily!$E$2:$E$2407)/3600 -> 11906.031 | E5: =SUMIF(Data_Daily!$A$2:$A$2407,$A5,Data_Daily!$F$2:$F$2407)/3600 -> 9245.5438 | F5: =SUMIF(Data_Daily!$A$2:$A$2407,$A5,Data_Daily!$I$2:$I$2407)/3600 -> 1393.3596 | G5: =SUMIF(Data_Daily!$A$2:$A$2407,$A5,Data_Daily!$J$2:$J$2407)/3600 -> 1267.1278 | H5: =SUMIF(Data_Daily!$A$2:$A$2407,$A5,Data_Daily!$H$2:$H$2407)/3600 -> 1540.7381 | I5: =SUMIF(Data_Daily!$A$2:$A$2407,$A5,Data_Daily!$K$2:$K$2407) -> 37086522 | J5: =SUMIF(Data_Daily!$A$2:$A$2407,$A5,Data_Daily!$L$2:$L$2407) -> 31286632 | K5: =SUMIF(Data_Daily!$A$2:$A$2407,$A5,Data_Daily!$M$2:$M$2407) -> 31148051 | L5: =E5/D5 -> 0.77654288 | M5: =MIN(J5/I5,1) -> 0.84361192 | N5: =K5/J5 -> 0.9955706 | O5: =L5*M5*N5 -> 0.65219913 | P5: =(O5-Inputs!$B$5)*100 -> 0.21991283 | Q5: =E5/B5 -> 0.68698751
A6: s_2 | B6: =SUMIF(Data_Daily!$A$2:$A$2407,$A6,Data_Daily!$C$2:$C$2407)/3600 -> 5532.4767 | C6: =SUMIF(Data_Daily!$A$2:$A$2407,$A6,Data_Daily!$D$2:$D$2407)/3600 -> 1369.1251 | D6: =SUMIF(Data_Daily!$A$2:$A$2407,$A6,Data_Daily!$E$2:$E$2407)/3600 -> 4163.3515 | E6: =SUMIF(Data_Daily!$A$2:$A$2407,$A6,Data_Daily!$F$2:$F$2407)/3600 -> 1719.7614 | F6: =SUMIF(Data_Daily!$A$2:$A$2407,$A6,Data_Daily!$I$2:$I$2407)/3600 -> 573.78872 | G6: =SUMIF(Data_Daily!$A$2:$A$2407,$A6,Data_Daily!$J$2:$J$2407)/3600 -> 1869.8014 | H6: =SUMIF(Data_Daily!$A$2:$A$2407,$A6,Data_Daily!$H$2:$H$2407)/3600 -> 363.36303 | I6: =SUMIF(Data_Daily!$A$2:$A$2407,$A6,Data_Daily!$K$2:$K$2407) -> 10628003 | J6: =SUMIF(Data_Daily!$A$2:$A$2407,$A6,Data_Daily!$L$2:$L$2407) -> 8337448 | K6: =SUMIF(Data_Daily!$A$2:$A$2407,$A6,Data_Daily!$M$2:$M$2407) -> 8292863 | L6: =E6/D6 -> 0.41307139 | M6: =MIN(J6/I6,1) -> 0.78447924 | N6: =K6/J6 -> 0.99465244 | O6: =L6*M6*N6 -> 0.32231308 | P6: =(O6-Inputs!$B$5)*100 -> -32.768692 | Q6: =E6/B6 -> 0.31084838
A7: s_3 | B7: =SUMIF(Data_Daily!$A$2:$A$2407,$A7,Data_Daily!$C$2:$C$2407)/3600 -> 7450.6406 | C7: =SUMIF(Data_Daily!$A$2:$A$2407,$A7,Data_Daily!$D$2:$D$2407)/3600 -> 690.68448 | D7: =SUMIF(Data_Daily!$A$2:$A$2407,$A7,Data_Daily!$E$2:$E$2407)/3600 -> 6759.9561 | E7: =SUMIF(Data_Daily!$A$2:$A$2407,$A7,Data_Daily!$F$2:$F$2407)/3600 -> 3326.6326 | F7: =SUMIF(Data_Daily!$A$2:$A$2407,$A7,Data_Daily!$I$2:$I$2407)/3600 -> 466.29693 | G7: =SUMIF(Data_Daily!$A$2:$A$2407,$A7,Data_Daily!$J$2:$J$2407)/3600 -> 2967.0266 | H7: =SUMIF(Data_Daily!$A$2:$A$2407,$A7,Data_Daily!$H$2:$H$2407)/3600 -> 305.30328 | I7: =SUMIF(Data_Daily!$A$2:$A$2407,$A7,Data_Daily!$K$2:$K$2407) -> 13259061 | J7: =SUMIF(Data_Daily!$A$2:$A$2407,$A7,Data_Daily!$L$2:$L$2407) -> 11927022 | K7: =SUMIF(Data_Daily!$A$2:$A$2407,$A7,Data_Daily!$M$2:$M$2407) -> 11898514 | L7: =E7/D7 -> 0.4921086 | M7: =MIN(J7/I7,1) -> 0.89953746 | N7: =K7/J7 -> 0.9976098 | O7: =L7*M7*N7 -> 0.44161205 | P7: =(O7-Inputs!$B$5)*100 -> -20.838795 | Q7: =E7/B7 -> 0.44648947
A8: s_4 | B8: =SUMIF(Data_Daily!$A$2:$A$2407,$A8,Data_Daily!$C$2:$C$2407)/3600 -> 7350.8911 | C8: =SUMIF(Data_Daily!$A$2:$A$2407,$A8,Data_Daily!$D$2:$D$2407)/3600 -> 1219.3629 | D8: =SUMIF(Data_Daily!$A$2:$A$2407,$A8,Data_Daily!$E$2:$E$2407)/3600 -> 6131.5282 | E8: =SUMIF(Data_Daily!$A$2:$A$2407,$A8,Data_Daily!$F$2:$F$2407)/3600 -> 4238.2206 | F8: =SUMIF(Data_Daily!$A$2:$A$2407,$A8,Data_Daily!$I$2:$I$2407)/3600 -> 358.38358 | G8: =SUMIF(Data_Daily!$A$2:$A$2407,$A8,Data_Daily!$J$2:$J$2407)/3600 -> 1534.9241 | H8: =SUMIF(Data_Daily!$A$2:$A$2407,$A8,Data_Daily!$H$2:$H$2407)/3600 -> 1540.1006 | I8: =SUMIF(Data_Daily!$A$2:$A$2407,$A8,Data_Daily!$K$2:$K$2407) -> 23527932 | J8: =SUMIF(Data_Daily!$A$2:$A$2407,$A8,Data_Daily!$L$2:$L$2407) -> 15357768 | K8: =SUMIF(Data_Daily!$A$2:$A$2407,$A8,Data_Daily!$M$2:$M$2407) -> 15250883 | L8: =E8/D8 -> 0.69121766 | M8: =MIN(J8/I8,1) -> 0.6527462 | N8: =K8/J8 -> 0.99304033 | O8: =L8*M8*N8 -> 0.44804957 | P8: =(O8-Inputs!$B$5)*100 -> -20.195043 | Q8: =E8/B8 -> 0.57655875
A9: s_5 | B9: =SUMIF(Data_Daily!$A$2:$A$2407,$A9,Data_Daily!$C$2:$C$2407)/3600 -> 10338.45 | C9: =SUMIF(Data_Daily!$A$2:$A$2407,$A9,Data_Daily!$D$2:$D$2407)/3600 -> 1702.962 | D9: =SUMIF(Data_Daily!$A$2:$A$2407,$A9,Data_Daily!$E$2:$E$2407)/3600 -> 8635.4876 | E9: =SUMIF(Data_Daily!$A$2:$A$2407,$A9,Data_Daily!$F$2:$F$2407)/3600 -> 5652.7956 | F9: =SUMIF(Data_Daily!$A$2:$A$2407,$A9,Data_Daily!$I$2:$I$2407)/3600 -> 355.60755 | G9: =SUMIF(Data_Daily!$A$2:$A$2407,$A9,Data_Daily!$J$2:$J$2407)/3600 -> 2627.0845 | H9: =SUMIF(Data_Daily!$A$2:$A$2407,$A9,Data_Daily!$H$2:$H$2407)/3600 -> 1043.3275 | I9: =SUMIF(Data_Daily!$A$2:$A$2407,$A9,Data_Daily!$K$2:$K$2407) -> 33816047 | J9: =SUMIF(Data_Daily!$A$2:$A$2407,$A9,Data_Daily!$L$2:$L$2407) -> 28647997 | K9: =SUMIF(Data_Daily!$A$2:$A$2407,$A9,Data_Daily!$M$2:$M$2407) -> 28575884 | L9: =E9/D9 -> 0.65460062 | M9: =MIN(J9/I9,1) -> 0.84717166 | N9: =K9/J9 -> 0.99748279 | O9: =L9*M9*N9 -> 0.55316316 | P9: =(O9-Inputs!$B$5)*100 -> -9.6836844 | Q9: =E9/B9 -> 0.54677401
A10: Fleet | B10: =SUM(B5:B9) -> 44130.554 | C10: =SUM(C5:C9) -> 6534.1992 | D10: =SUM(D5:D9) -> 37596.355 | E10: =SUM(E5:E9) -> 24182.954 | F10: =SUM(F5:F9) -> 3147.4364 | G10: =SUM(G5:G9) -> 10265.964 | H10: =SUM(H5:H9) -> 4792.8325 | I10: =SUM(I5:I9) -> 1.1831757e+08 | ... K10: =SUM(K5:K9) -> 95166195 | L10: =E10/D10 -> 0.64322603 | M10: =MIN(J10/I10,1) -> 0.80763044 | N10: =K10/J10 -> 0.99591163 | O10: =L10*M10*N10 -> 0.51736506 | P10: =(O10-Inputs!$B$5)*100 -> -13.263494 | Q10: =E10/B10 -> 0.54798664

Sheet M3_LossTree
A1: M3 - Downtime / OEE loss tree (fleet)
A2: MEASURE. Parents are formulas; leaves come from M2 or v_loss_tree. Checks must read 0.
A4: Node | B4: Loss category | C4: Hours | D4: % of planned time | E4: Source
A5: 0 | B5: Logged time | C5: =M2_OEE!B10 -> 44130.554 | D5: =C5/$C$10 -> 1.1737987 | E5: M2
A6: 1 | B6: Scheduled downtime (planned, outside OEE) | C6: =M2_OEE!C10 -> 6534.1992 | D6: =C6/$C$10 -> 0.17379874 | E6: M2
A7: 1.1 | B7: Changeover / cleaning-like (10 min - 4 h) | C7: 5110.3056 | D7: =C7/$C$10 -> 0.13592556 | E7: v_loss_tree
A8: 1.2 | B8: Long shutdowns (> 4 h) | C8: 617.28883 | D8: =C8/$C$10 -> 0.016418848 | E8: v_loss_tree
A9: 1.3 | B9: Short planned stops (< 10 min) | C9: =C6-C7-C8 -> 806.60484 | D9: =C9/$C$10 -> 0.021454337 | E9: residual
A10: 2 | B10: Planned production time (PPT) | C10: =M2_OEE!D10 -> 37596.355 | D10: =C10/$C$10 -> 1 | E10: M2
A11: 2.1 | B11: Availability loss: alarm downtime | C11: =M2_OEE!F10 -> 3147.4364 | D11: =C11/$C$10 -> 0.083716532 | E11: M2
A12: 2.1.1 | B12: Alarm A_065 | C12: =M4_Pareto!C5 -> 857.92907 | D12: =C12/$C$10 -> 0.022819475 | E12: M4
A13: 2.1.2 | B13: Alarm A_101 | C13: =M4_Pareto!C6 -> 515.18852 | D13: =C13/$C$10 -> 0.013703151 | E13: M4
A14: 2.1.3 | B14: Alarm A_006 | C14: =M4_Pareto!C7 -> 411.22776 | D14: =C14/$C$10 -> 0.010937969 | E14: M4
A15: 2.1.4 | B15: Alarm A_001 | C15: =M4_Pareto!C8 -> 387.56895 | D15: =C15/$C$10 -> 0.010308684 | E15: M4
A16: 2.1.5 | B16: Alarm A_066 | C16: =M4_Pareto!C9 -> 153.42251 | D16: =C16/$C$10 -> 0.0040807815 | E16: M4
A17: 2.1.6 | B17: Other alarms | C17: =C11-SUM(C12:C16) -> 822.09961 | D17: =C17/$C$10 -> 0.021866471 | E17: residual
A18: 2.2 | B18: Availability loss: idle (no reason code) | C18: =M2_OEE!G10 -> 10265.964 | D18: =C18/$C$10 -> 0.27305744 | E18: M2
A19: 3 | B19: Run time | C19: =M2_OEE!E10 -> 24182.954 | D19: =C19/$C$10 -> 0.64322603 | E19: M2
A20: 3.1 | B20: Performance loss: reduced speed / minor stops | C20: 4463.6361 | D20: =C20/$C$10 -> 0.11872524 | E20: v_loss_tree
A21: 3.2 | B21: Performance loss: sub-rated running | C21: =C19-C22-C20 -> 188.42815 | D21: =C21/$C$10 -> 0.0050118729 | E21: residual
A22: 4 | B22: Net run time | C22: =C19*M2_OEE!M10 -> 19530.89 | D22: =C22/$C$10 -> 0.51948892 | E22: Run x P
A23: 4.1 | B23: Quality loss: rejects | C23: =C22-C24 -> 79.849538 | D23: =C23/$C$10 -> 0.0021238638 | E23: residual
A24: 5 | B24: Fully productive time (= OEE x PPT) | C24: =C22*M2_OEE!N10 -> 19451.04 | D24: =C24/$C$10 -> 0.51736506 | E24: Net x Q
B28: Check: PPT - (downtime + idle + run) = | C28: =C10-C11-C18-C19 -> 0
B29: Check: fully productive / PPT - OEE = | C29: =C24/C10-M2_OEE!O10 -> 0

Sheet M4_Pareto
A1: M4 - Pareto of alarm downtime (fleet)
A2: MEASURE. From v_pareto_alarm. Share, cumulative % and ABC class are formulas.
A4: Alarm | B4: Stops | C4: Downtime h | D4: MTTR min | E4: Machines | F4: Share | G4: Cumulative % | H4: Class | I4: Rank | K4: Vital few (class A codes) | L4: =COUNTIF(H5:H136,"A") -> 7
A5: A_065 | B5: 18864 | C5: 857.92907 | D5: 2.728782 | E5: 1 | F5: =C5/SUM($C$5:$C$136) -> 0.27258027 | G5: =SUM($C$5:C5)/SUM($C$5:$C$136) -> 0.27258027 | H5: =IF(G5-F5<0.8,"A",IF(G5-F5<0.95,"B","C")) -> A | I5: =RANK(C5,$C$5:$C$136) -> 1 | K5: Total alarm codes | L5: =COUNTA(A5:A136) -> 132
A6: A_101 | B6: 18399 | C6: 515.18852 | D6: 1.6800539 | E6: 3 | F6: =C6/SUM($C$5:$C$136) -> 0.16368512 | G6: =SUM($C$5:C6)/SUM($C$5:$C$136) -> 0.43626539 | H6: =IF(G6-F6<0.8,"A",IF(G6-F6<0.95,"B","C")) -> A | I6: =RANK(C6,$C$5:$C$136) -> 2 | K6: Class A share of downtime | L6: =SUMIF(H5:H136,"A",C5:C136)/SUM(C5:C136) -> 0.81591303
A7: A_006 | B7: 3922 | C7: 411.22776 | D7: 6.2910927 | E7: 4 | F7: =C7/SUM($C$5:$C$136) -> 0.13065483 | G7: =SUM($C$5:C7)/SUM($C$5:$C$136) -> 0.56692022 | H7: =IF(G7-F7<0.8,"A",IF(G7-F7<0.95,"B","C")) -> A | I7: =RANK(C7,$C$5:$C$136) -> 3
A8: A_001 | B8: 4401 | C8: 387.56895 | D8: 5.2838303 | E8: 4 | F8: =C8/SUM($C$5:$C$136) -> 0.12313798 | G8: =SUM($C$5:C8)/SUM($C$5:$C$136) -> 0.6900582 | H8: =IF(G8-F8<0.8,"A",IF(G8-F8<0.95,"B","C")) -> A | I8: =RANK(C8,$C$5:$C$136) -> 4
A9: A_066 | B9: 3375 | C9: 153.42251 | D9: 2.7275113 | E9: 2 | F9: =C9/SUM($C$5:$C$136) -> 0.048745229 | G9: =SUM($C$5:C9)/SUM($C$5:$C$136) -> 0.73880343 | H9: =IF(G9-F9<0.8,"A",IF(G9-F9<0.95,"B","C")) -> A | I9: =RANK(C9,$C$5:$C$136) -> 5
A10: A_005 | B10: 12225 | C10: 131.56096 | D10: 0.64569796 | E10: 5 | F10: =C10/SUM($C$5:$C$136) -> 0.041799402 | G10: =SUM($C$5:C10)/SUM($C$5:$C$136) -> 0.78060283 | H10: =IF(G10-F10<0.8,"A",IF(G10-F10<0.95,"B","C")) -> A | I10: =RANK(C10,$C$5:$C$136) -> 6
A11: A_020 | B11: 5098 | C11: 111.13663 | D11: 1.3080027 | E11: 5 | F11: =C11/SUM($C$5:$C$136) -> 0.035310206 | G11: =SUM($C$5:C11)/SUM($C$5:$C$136) -> 0.81591303 | H11: =IF(G11-F11<0.8,"A",IF(G11-F11<0.95,"B","C")) -> A | I11: =RANK(C11,$C$5:$C$136) -> 7
A12: A_010 | B12: 9275 | C12: 90.552497 | D12: 0.58578435 | E12: 5 | F12: =C12/SUM($C$5:$C$136) -> 0.028770239 | G12: =SUM($C$5:C12)/SUM($C$5:$C$136) -> 0.84468327 | H12: =IF(G12-F12<0.8,"A",IF(G12-F12<0.95,"B","C")) -> B | I12: =RANK(C12,$C$5:$C$136) -> 8
A13: A_016 | B13: 1142 | C13: 53.243437 | D13: 2.7973785 | E13: 5 | F13: =C13/SUM($C$5:$C$136) -> 0.016916445 | G13: =SUM($C$5:C13)/SUM($C$5:$C$136) -> 0.86159972 | H13: =IF(G13-F13<0.8,"A",IF(G13-F13<0.95,"B","C")) -> B | I13: =RANK(C13,$C$5:$C$136) -> 9
A14: A_003 | B14: 2225 | C14: 42.132123 | D14: 1.1361471 | E14: 5 | F14: =C14/SUM($C$5:$C$136) -> 0.013386171 | G14: =SUM($C$5:C14)/SUM($C$5:$C$136) -> 0.87498589 | H14: =IF(G14-F14<0.8,"A",IF(G14-F14<0.95,"B","C")) -> B | I14: =RANK(C14,$C$5:$C$136) -> 10
A15: A_067 | B15: 831 | C15: 40.946963 | D15: 2.9564594 | E15: 1 | F15: =C15/SUM($C$5:$C$136) -> 0.013009624 | G15: =SUM($C$5:C15)/SUM($C$5:$C$136) -> 0.88799551 | H15: =IF(G15-F15<0.8,"A",IF(G15-F15<0.95,"B","C")) -> B | I15: =RANK(C15,$C$5:$C$136) -> 11
A16: A_017 | B16: 1763 | C16: 37.191145 | D16: 1.2657225 | E16: 5 | F16: =C16/SUM($C$5:$C$136) -> 0.011816329 | G16: =SUM($C$5:C16)/SUM($C$5:$C$136) -> 0.89981184 | H16: =IF(G16-F16<0.8,"A",IF(G16-F16<0.95,"B","C")) -> B | I16: =RANK(C16,$C$5:$C$136) -> 12
A17: A_012 | B17: 1161 | C17: 36.3385 | D17: 1.8779587 | E17: 4 | F17: =C17/SUM($C$5:$C$136) -> 0.011545428 | G17: =SUM($C$5:C17)/SUM($C$5:$C$136) -> 0.91135727 | H17: =IF(G17-F17<0.8,"A",IF(G17-F17<0.95,"B","C")) -> B | I17: =RANK(C17,$C$5:$C$136) -> 13
A18: A_011 | B18: 1150 | C18: 36.107499 | D18: 1.8838695 | E18: 4 | F18: =C18/SUM($C$5:$C$136) -> 0.011472034 | G18: =SUM($C$5:C18)/SUM($C$5:$C$136) -> 0.9228293 | H18: =IF(G18-F18<0.8,"A",IF(G18-F18<0.95,"B","C")) -> B | I18: =RANK(C18,$C$5:$C$136) -> 14
... A136: A_107 | B136: 1 | C136: 0.0012972222 | D136: 0.077833333 | E136: 1 | F136: =C136/SUM($C$5:$C$136) -> 4.12152e-07 | G136: =SUM($C$5:C136)/SUM($C$5:$C$136) -> 1 | H136: =IF(G136-F136<0.8,"A",IF(G136-F136<0.95,"B","C")) -> C | I136: =RANK(C136,$C$5:$C$136) -> 132

Sheet M5_Reliability
A1: M5 - Reliability: MTBF / MTTR
A2: MEASURE. Stops/downtime from v_reliability; run hours linked from M2.
A4: Machine | B4: Alarm stops | C4: Downtime h | D4: Run h | E4: MTBF (run-min) | F4: MTTR (min) | G4: Inherent availability | H4: Stops per run-hour
A5: s_1 | B5: 32576 | C5: 1393.3596 | D5: =M2_OEE!E5 -> 9245.5438 | E5: =D5/B5*60 -> 17.028875 | F5: =C5/B5*60 -> 2.5663549 | G5: =E5/(E5+F5) -> 0.86903165 | H5: =B5/D5 -> 3.5234272
A6: s_2 | B6: 17361 | C6: 573.78872 | D6: =M2_OEE!E6 -> 1719.7614 | E6: =D6/B6*60 -> 5.9435335 | F6: =C6/B6*60 -> 1.9830265 | G6: =E6/(E6+F6) -> 0.74982508 | H6: =B6/D6 -> 10.095005
A7: s_3 | B7: 7777 | C7: 466.29693 | D7: =M2_OEE!E7 -> 3326.6326 | E7: =D7/B7*60 -> 25.665161 | F7: =C7/B7*60 -> 3.5975075 | G7: =E7/(E7+F7) -> 0.87706153 | H7: =B7/D7 -> 2.3377995
A8: s_4 | B8: 18250 | C8: 358.38358 | D8: =M2_OEE!E8 -> 4238.2206 | E8: =D8/B8*60 -> 13.933876 | F8: =C8/B8*60 -> 1.1782474 | G8: =E8/(E8+F8) -> 0.92203297 | H8: =B8/D8 -> 4.3060525
A9: s_5 | B9: 16041 | C9: 355.60755 | D9: =M2_OEE!E9 -> 5652.7956 | E9: =D9/B9*60 -> 21.143802 | F9: =C9/B9*60 -> 1.3301199 | G9: =E9/(E9+F9) -> 0.94081496 | H9: =B9/D9 -> 2.837711
A10: Fleet | B10: =SUM(B5:B9) -> 92005 | C10: =SUM(C5:C9) -> 3147.4364 | D10: =SUM(D5:D9) -> 24182.954 | E10: =D10/B10*60 -> 15.770635 | F10: =C10/B10*60 -> 2.0525644 | G10: =E10/(E10+F10) -> 0.88483749 | H10: =B10/D10 -> 3.8045394
A12: Reading: MTTR of 1-4 min and MTBF of 6-26 run-minutes = MINOR STOPS, not breakdowns. That points to Kaizen, autonomous maintenance and Poka-Yoke rather than spare parts or big repairs.

Sheet M6_Sigma
A1: M6 - Six Sigma baseline: DPMO and sigma level
A2: MEASURE. Sigma (short-term) = NORMSINV(yield) + 1.5 shift.
A4: Scope | B4: Opportunities (units in) | C4: Defects | D4: DPMO | E4: Yield | F4: Sigma level (ST)
A5: s_1 - package rejects | B5: =M2_OEE!J5 -> 31286632 | C5: =M2_OEE!J5-M2_OEE!K5 -> 138581 | D5: =C5/B5*1000000 -> 4429.3998 | E5: =1-C5/B5 -> 0.9955706 | F5: =NORMSINV(E5)+1.5 -> 4.1174557
A6: s_2 - package rejects | B6: =M2_OEE!J6 -> 8337448 | C6: =M2_OEE!J6-M2_OEE!K6 -> 44585 | D6: =C6/B6*1000000 -> 5347.5596 | E6: =1-C6/B6 -> 0.99465244 | F6: =NORMSINV(E6)+1.5 -> 4.0525056
A7: s_3 - package rejects | B7: =M2_OEE!J7 -> 11927022 | C7: =M2_OEE!J7-M2_OEE!K7 -> 28508 | D7: =C7/B7*1000000 -> 2390.2027 | E7: =1-C7/B7 -> 0.9976098 | F7: =NORMSINV(E7)+1.5 -> 4.3214704
A8: s_4 - package rejects | B8: =M2_OEE!J8 -> 15357768 | C8: =M2_OEE!J8-M2_OEE!K8 -> 106885 | D8: =C8/B8*1000000 -> 6959.6702 | E8: =1-C8/B8 -> 0.99304033 | F8: =NORMSINV(E8)+1.5 -> 3.9593383
A9: s_5 - package rejects | B9: =M2_OEE!J9 -> 28647997 | C9: =M2_OEE!J9-M2_OEE!K9 -> 72113 | D9: =C9/B9*1000000 -> 2517.2091 | E9: =1-C9/B9 -> 0.99748279 | F9: =NORMSINV(E9)+1.5 -> 4.3048232
A10: Fleet - package rejects | B10: =M2_OEE!J10 -> 95556867 | C10: =M2_OEE!J10-M2_OEE!K10 -> 390672 | D10: =C10/B10*1000000 -> 4088.3718 | E10: =1-C10/B10 -> 0.99591163 | F10: =NORMSINV(E10)+1.5 -> 4.1446832
A11: s_1 - days below OEE target (X-bar subgroups) | B11: =COUNT(C1_XbarR_s1!F16:F2000) -> 479 | C11: =COUNTIF(C1_XbarR_s1!F16:F2000,"<"&Inputs!B5) -> 221 | D11: =C11/B11*1000000 -> 461377.87 | E11: =1-C11/B11 -> 0.53862213 | F11: =NORMSINV(E11)+1.5 -> 1.596963
A13: Reading: package quality is already ~4 sigma, so quality is NOT the problem. Measured against the OEE target, s_1 is only a ~1.6-sigma process: time loss, not defects, is the defect that matters.

Sheet A1_RCA
A1: A1 - Root cause analysis: Fishbone (6M) + 5 Whys
A2: ANALYZE. [data] = verified in PIADE; [hyp.] = must be verified at the gemba before acting.
A4: 6M category | B4: Potential cause | C4: Evidence | D4: Status
A5: Machine | B5: A_065 micro-stops on s_1 | C5: 858 h, 18,864 stops, MTTR 2.7 min (M4) | D5: [data]
A6: Machine | B6: A_101 repeat stops on s_2/s_3/s_5 | C6: 515 h; 70% recur within 30 min (A2) | D6: [data]
A7: Machine | B7: A_001 / A_006 long stops | C7: MTTR 5-6 min, highest RPN (A2) | D7: [data]
A8: Machine | B8: Reduced-speed running on s_4 | C8: 21% of s_4 logged time in performance_loss state | D8: [data]
A9: Method | B9: Changeovers not standardised | C9: Mean 37-68 min, P90 up to 167 min (I3) | D9: [data]
A10: Method | B10: Start-of-day restarts | C10: Shift A alarm-downtime share highest (A3) | D10: [data]
A11: Measurement | B11: Idle has no reason code | C11: 27% of PPT unexplained (M1, M3) | D11: [data]
A12: Measurement | B12: Alarm codes anonymised, no hierarchy | C12: 132 codes, no family / component map | D12: [data]
A13: People | B13: Night and weekend under-staffing | C13: Idle share C shift and weekends significantly higher (A3) | D13: [data]
A14: People | B14: Recovery skill varies by operator | C14: Not in data - verify with MTTR by crew | D14: [hyp.]
A15: Material | B15: Line starvation behind idle | C15: Not coded - verify with reason codes | D15: [hyp.]
... A17: Environment | B17: s_1 degraded in 2021 | C17: s_1 OEE 67.8% -> 62.7%; all other machines improved (A3) | D17: [data]
A19: 5 Whys - A_065 on s_1
A20: Why? | B20: Answer | C20: Evidence / status
A21: 1. Why is s_1 OEE below target? | B21: Availability loss from frequent alarm stops | C21: A_065 = 62% of s_1 alarm downtime [data]
A22: 2. Why so much A_065 downtime? | B22: Very frequent short stops (~2 per run-hour), not long ones | C22: Median 1.3 min, 18.9k events [data]
A23: 3. Why so frequent? | B23: Stops cluster: 81% recur within 30 min of the previous one | C23: Repeat rate [data]
A24: 4. Why do they recur? | B24: Operator clears the jam but the trigger condition is not removed | C24: [hyp.] - observe 20 stops at the gemba
A25: 5. Why is the trigger not removed? | B25: No standard for root-cause fixing of micro-stops; no CIL routine | C25: [hyp.] -> Kaizen + CIL + Poka-Yoke
A27: 5 Whys - Idle time
A28: Why? | B28: Answer | C28: Evidence / status
A29: 1. Why is availability only 64%? | B29: 27% of planned time is idle | C29: M3 [data]
A30: 2. Why is the machine idle? | B30: Unknown - idle rows carry no reason code | C30: M1 [data]
A31: 3. When is it idle? | B31: Night shift (C) and weekends | C31: A3 ANOVA / t-test [data]
A32: 4. Why then? | B32: Likely thin staffing / no material staged / no orders | C32: [hyp.]
A33: 5. Why can't we tell? | B33: The data system never asks the operator why | C33: Root cause = measurement gap -> Poka-Yoke on data entry

Sheet A2_FMEA
A1: A2 - Data-driven FMEA (top 10 failure modes by downtime)
A2: ANALYZE. S from MTTR, O from stops per 1,000 run-hours, D from 'repeat within 30 min' (a failure that recurs announces itself -> easier to detect). Scales at right.
A4: Failure mode | B4: Machines | C4: Effect | D4: Stops | E4: Downtime h | F4: MTTR min | G4: Stops / 1000 run-h | H4: Repeat <= 30 min | I4: S | J4: O | K4: D | L4: RPN | M4: Priority | N4: Recommended action | Q4: MTTR >= (min) | R4: S | T4: Stops/1000h >= | U4: O
A5: A_065 | B5: s_1 | C5: Machine stop, lost output | D5: 18864 | E5: 857.92907 | F5: 2.728782 | G5: 2040.3343 | H5: 0.80550254 | I5: =LOOKUP(F5,$Q$5:$Q$14,$R$5:$R$14) -> 4 | J5: =LOOKUP(G5,$T$5:$T$14,$U$5:$U$14) -> 8 | K5: =MAX(2,MIN(10,ROUND(10-8*H5,0))) -> 4 | L5: =I5*J5*K5 -> 128 | M5: =IF(L5>=200,"High",IF(L5>=120,"Medium","Low")) -> Medium | N5: =IF(I5>=6,"Poka-Yoke + standard repair kit (long stops)",IF(J5>=8,"Kaizen blitz: high-frequency micro-stop","5S / visual control + monitor")) -> Kaizen blitz: high-frequency micro-stop | Q5: 0 | R5: 1 | T5: 0 | U5: 1
A6: A_101 | B6: s_2, s_3, s_5 | C6: Machine stop, lost output | D6: 18399 | E6: 515.18852 | F6: 1.6800539 | G6: 1719.663 | H6: 0.70253818 | I6: =LOOKUP(F6,$Q$5:$Q$14,$R$5:$R$14) -> 3 | J6: =LOOKUP(G6,$T$5:$T$14,$U$5:$U$14) -> 8 | K6: =MAX(2,MIN(10,ROUND(10-8*H6,0))) -> 4 | L6: =I6*J6*K6 -> 96 | M6: =IF(L6>=200,"High",IF(L6>=120,"Medium","Low")) -> Low | N6: =IF(I6>=6,"Poka-Yoke + standard repair kit (long stops)",IF(J6>=8,"Kaizen blitz: high-frequency micro-stop","5S / visual control + monitor")) -> Kaizen blitz: high-frequency micro-stop | Q6: 0.5 | R6: 2 | T6: 1 | U6: 2
A7: A_006 | B7: s_1, s_2, s_3, s_4 | C7: Machine stop, lost output | D7: 3922 | E7: 411.22776 | F7: 6.2910927 | G7: 211.65496 | H7: 0.2763896 | I7: =LOOKUP(F7,$Q$5:$Q$14,$R$5:$R$14) -> 6 | J7: =LOOKUP(G7,$T$5:$T$14,$U$5:$U$14) -> 6 | K7: =MAX(2,MIN(10,ROUND(10-8*H7,0))) -> 8 | L7: =I7*J7*K7 -> 288 | M7: =IF(L7>=200,"High",IF(L7>=120,"Medium","Low")) -> High | N7: =IF(I7>=6,"Poka-Yoke + standard repair kit (long stops)",IF(J7>=8,"Kaizen blitz: high-frequency micro-stop","5S / visual control + monitor")) -> Poka-Yoke + standard repair kit (long stops) | Q7: 1 | R7: 3 | T7: 3 | U7: 3
A8: A_001 | B8: s_1, s_2, s_3, s_4 | C8: Machine stop, lost output | D8: 4401 | E8: 387.56895 | F8: 5.2838303 | G8: 237.50472 | H8: 0.14928425 | I8: =LOOKUP(F8,$Q$5:$Q$14,$R$5:$R$14) -> 6 | J8: =LOOKUP(G8,$T$5:$T$14,$U$5:$U$14) -> 6 | K8: =MAX(2,MIN(10,ROUND(10-8*H8,0))) -> 9 | L8: =I8*J8*K8 -> 324 | M8: =IF(L8>=200,"High",IF(L8>=120,"Medium","Low")) -> High | N8: =IF(I8>=6,"Poka-Yoke + standard repair kit (long stops)",IF(J8>=8,"Kaizen blitz: high-frequency micro-stop","5S / visual control + monitor")) -> Poka-Yoke + standard repair kit (long stops) | Q8: 2 | R8: 4 | T8: 10 | U8: 4
A9: A_066 | B9: s_1, s_5 | C9: Machine stop, lost output | D9: 3375 | E9: 153.42251 | F9: 2.7275113 | G9: 226.53532 | H9: 0.6717037 | I9: =LOOKUP(F9,$Q$5:$Q$14,$R$5:$R$14) -> 4 | J9: =LOOKUP(G9,$T$5:$T$14,$U$5:$U$14) -> 6 | K9: =MAX(2,MIN(10,ROUND(10-8*H9,0))) -> 5 | L9: =I9*J9*K9 -> 120 | M9: =IF(L9>=200,"High",IF(L9>=120,"Medium","Low")) -> Medium | N9: =IF(I9>=6,"Poka-Yoke + standard repair kit (long stops)",IF(J9>=8,"Kaizen blitz: high-frequency micro-stop","5S / visual control + monitor")) -> 5S / visual control + monitor | Q9: 3 | R9: 5 | T9: 30 | U9: 5
A10: A_005 | B10: s_1, s_2, s_3, s_4, s_5 | C10: Machine stop, lost output | D10: 12225 | E10: 131.56096 | F10: 0.64569796 | G10: 505.52137 | H10: 0.69063395 | I10: =LOOKUP(F10,$Q$5:$Q$14,$R$5:$R$14) -> 2 | J10: =LOOKUP(G10,$T$5:$T$14,$U$5:$U$14) -> 7 | K10: =MAX(2,MIN(10,ROUND(10-8*H10,0))) -> 4 | L10: =I10*J10*K10 -> 56 | M10: =IF(L10>=200,"High",IF(L10>=120,"Medium","Low")) -> Low | N10: =IF(I10>=6,"Poka-Yoke + standard repair kit (long stops)",IF(J10>=8,"Kaizen blitz: high-frequency micro-stop","5S / visual control + monitor")) -> 5S / visual control + monitor | Q10: 5 | R10: 6 | T10: 100 | U10: 6
A11: A_020 | B11: s_1, s_2, s_3, s_4, s_5 | C11: Machine stop, lost output | D11: 5098 | E11: 111.13663 | F11: 1.3080027 | G11: 210.80965 | H11: 0.51824245 | I11: =LOOKUP(F11,$Q$5:$Q$14,$R$5:$R$14) -> 3 | J11: =LOOKUP(G11,$T$5:$T$14,$U$5:$U$14) -> 6 | K11: =MAX(2,MIN(10,ROUND(10-8*H11,0))) -> 6 | L11: =I11*J11*K11 -> 108 | M11: =IF(L11>=200,"High",IF(L11>=120,"Medium","Low")) -> Low | N11: =IF(I11>=6,"Poka-Yoke + standard repair kit (long stops)",IF(J11>=8,"Kaizen blitz: high-frequency micro-stop","5S / visual control + monitor")) -> 5S / visual control + monitor | Q11: 10 | R11: 7 | T11: 300 | U11: 7
A12: A_010 | B12: s_1, s_2, s_3, s_4, s_5 | C12: Machine stop, lost output | D12: 9275 | E12: 90.552497 | F12: 0.58578435 | G12: 383.53462 | H12: 0.61455526 | I12: =LOOKUP(F12,$Q$5:$Q$14,$R$5:$R$14) -> 2 | J12: =LOOKUP(G12,$T$5:$T$14,$U$5:$U$14) -> 7 | K12: =MAX(2,MIN(10,ROUND(10-8*H12,0))) -> 5 | L12: =I12*J12*K12 -> 70 | M12: =IF(L12>=200,"High",IF(L12>=120,"Medium","Low")) -> Low | N12: =IF(I12>=6,"Poka-Yoke + standard repair kit (long stops)",IF(J12>=8,"Kaizen blitz: high-frequency micro-stop","5S / visual control + monitor")) -> 5S / visual control + monitor | Q12: 20 | R12: 8 | T12: 1000 | U12: 8
A13: A_016 | B13: s_1, s_2, s_3, s_4, s_5 | C13: Machine stop, lost output | D13: 1142 | E13: 53.243437 | F13: 2.7973785 | G13: 47.223346 | H13: 0.1357268 | I13: =LOOKUP(F13,$Q$5:$Q$14,$R$5:$R$14) -> 4 | J13: =LOOKUP(G13,$T$5:$T$14,$U$5:$U$14) -> 5 | K13: =MAX(2,MIN(10,ROUND(10-8*H13,0))) -> 9 | L13: =I13*J13*K13 -> 180 | M13: =IF(L13>=200,"High",IF(L13>=120,"Medium","Low")) -> Medium | N13: =IF(I13>=6,"Poka-Yoke + standard repair kit (long stops)",IF(J13>=8,"Kaizen blitz: high-frequency micro-stop","5S / visual control + monitor")) -> 5S / visual control + monitor | Q13: 60 | R13: 9 | T13: 3000 | U13: 9
A14: A_003 | B14: s_1, s_2, s_3, s_4, s_5 | C14: Machine stop, lost output | D14: 2225 | E14: 42.132123 | F14: 1.1361471 | G14: 92.006957 | H14: 0.54741573 | I14: =LOOKUP(F14,$Q$5:$Q$14,$R$5:$R$14) -> 3 | J14: =LOOKUP(G14,$T$5:$T$14,$U$5:$U$14) -> 5 | K14: =MAX(2,MIN(10,ROUND(10-8*H14,0))) -> 6 | L14: =I14*J14*K14 -> 90 | M14: =IF(L14>=200,"High",IF(L14>=120,"Medium","Low")) -> Low | N14: =IF(I14>=6,"Poka-Yoke + standard repair kit (long stops)",IF(J14>=8,"Kaizen blitz: high-frequency micro-stop","5S / visual control + monitor")) -> 5S / visual control + monitor | Q14: 120 | R14: 10 | T14: 10000 | U14: 10
A16: Reading: Pareto ranks by impact (A_065 first); FMEA ranks by risk (A_001 / A_006 first - long, unpredictable stops). Use both: Kaizen for the frequent ones, Poka-Yoke for the risky ones.

Sheet A3_Hypothesis
A1: A3 - Hypothesis tests (Excel-native formulas, alpha = 0.05)
A2: ANALYZE. Data_Shift = v_shift_state_share (machine x day x shift, planned >= 1 h); Data_Daily = v_daily_machine. Large n makes ANOVA / Welch robust to non-normality.
A4: H1: Mean IDLE share is equal across shifts A, B, C (one-way ANOVA) | F4: H2: Mean ALARM-DOWNTIME share is equal across shifts (one-way ANOVA)
A5: Shift | B5: n | C5: Mean idle share | D5: SS within | F5: Shift | G5: n | H5: Mean downtime share | I5: SS within
A6: A | B6: =COUNTIF(Data_Shift!$C$2:$C$5993,A6) -> 2177 | C6: =AVERAGEIF(Data_Shift!$C$2:$C$5993,A6,Data_Shift!$D$2:$D$5993) -> 0.27023631 | D6: =SUMPRODUCT((Data_Shift!$C$2:$C$5993=A6)*(Data_Shift!$D$2:$D$5993-C6)^2) -> 186.85844 | F6: A | G6: =COUNTIF(Data_Shift!$C$2:$C$5993,F6) -> 2177 | H6: =AVERAGEIF(Data_Shift!$C$2:$C$5993,F6,Data_Shift!$E$2:$E$5993) -> 0.097862605 | I6: =SUMPRODUCT((Data_Shift!$C$2:$C$5993=F6)*(Data_Shift!$E$2:$E$5993-H6)^2) -> 18.850037
A7: B | B7: =COUNTIF(Data_Shift!$C$2:$C$5993,A7) -> 1741 | C7: =AVERAGEIF(Data_Shift!$C$2:$C$5993,A7,Data_Shift!$D$2:$D$5993) -> 0.19432885 | D7: =SUMPRODUCT((Data_Shift!$C$2:$C$5993=A7)*(Data_Shift!$D$2:$D$5993-C7)^2) -> 131.54663 | F7: B | G7: =COUNTIF(Data_Shift!$C$2:$C$5993,F7) -> 1741 | H7: =AVERAGEIF(Data_Shift!$C$2:$C$5993,F7,Data_Shift!$E$2:$E$5993) -> 0.075882718 | I7: =SUMPRODUCT((Data_Shift!$C$2:$C$5993=F7)*(Data_Shift!$E$2:$E$5993-H7)^2) -> 10.954488
A8: C | B8: =COUNTIF(Data_Shift!$C$2:$C$5993,A8) -> 2074 | C8: =AVERAGEIF(Data_Shift!$C$2:$C$5993,A8,Data_Shift!$D$2:$D$5993) -> 0.38522322 | D8: =SUMPRODUCT((Data_Shift!$C$2:$C$5993=A8)*(Data_Shift!$D$2:$D$5993-C8)^2) -> 316.60335 | F8: C | G8: =COUNTIF(Data_Shift!$C$2:$C$5993,F8) -> 2074 | H8: =AVERAGEIF(Data_Shift!$C$2:$C$5993,F8,Data_Shift!$E$2:$E$5993) -> 0.074793263 | I8: =SUMPRODUCT((Data_Shift!$C$2:$C$5993=F8)*(Data_Shift!$E$2:$E$5993-H8)^2) -> 22.135329
A9: Grand mean | B9: =SUMPRODUCT(B6:B8,C6:C8)/SUM(B6:B8) -> 0.2879813 | F9: Grand mean | G9: =SUMPRODUCT(G6:G8,H6:H8)/SUM(G6:G8) -> 0.08349131
A10: SS between | B10: =SUMPRODUCT(B6:B8,(C6:C8-B9)^2) -> 35.567159 | F10: SS between | G10: =SUMPRODUCT(G6:G8,(H6:H8-G9)^2) -> 0.70732298
A11: SS within | B11: =SUM(D6:D8) -> 635.00843 | F11: SS within | G11: =SUM(I6:I8) -> 51.939853
A12: df between / within | B12: =2 -> 2 | F12: df between | G12: =2 -> 2
B13: =SUM(B6:B8)-3 -> 5989 | F13: df within | G13: =SUM(G6:G8)-3 -> 5989
A14: F statistic | B14: =(B10/B12)/(B11/B13) -> 167.72353 | F14: F statistic | G14: =(G10/G12)/(G11/G13) -> 40.77945
A15: p-value | B15: =FDIST(B14,B12,B13) -> 1.334838e-71 | F15: p-value | G15: =FDIST(G14,G12,G13) -> 2.5657619e-18
A16: Decision | B16: =IF(B15<0.05,"Reject H0: idle differs by shift","Fail to reject H0") -> Reject H0: idle differs by shift | F16: Decision | G16: =IF(G15<0.05,"Reject H0: downtime differs by shift","Fail to reject H0") -> Reject H0: downtime differs by shift
A19: H3: Weekend idle share <= weekday idle share (Welch two-sample t, one-tailed) | F19: H4: Top-alarm mix is independent of shift (chi-square test of independence)
A20: Group | B20: n | C20: Mean | D20: Variance | F20: Alarm group | G20: Shift A | H20: Shift B | I20: Shift C | J20: Row total
A21: Weekend | B21: =COUNTIF(Data_Shift!$F$2:$F$5993,1) -> 1362 | C21: =AVERAGEIF(Data_Shift!$F$2:$F$5993,1,Data_Shift!$D$2:$D$5993) -> 0.35944137 | D21: =SUMPRODUCT((Data_Shift!$F$2:$F$5993=1)*(Data_Shift!$D$2:$D$5993-C21)^2)/(B21-1) -> 0.13890488 | F21: A_001 | G21: 2718 | H21: 616 | I21: 1067 | J21: =SUM(G21:I21) -> 4401
A22: Weekday | B22: =COUNTIF(Data_Shift!$F$2:$F$5993,0) -> 4630 | C22: =AVERAGEIF(Data_Shift!$F$2:$F$5993,0,Data_Shift!$D$2:$D$5993) -> 0.26696 | D22: =SUMPRODUCT((Data_Shift!$F$2:$F$5993=0)*(Data_Shift!$D$2:$D$5993-C22)^2)/(B22-1) -> 0.10207927 | F22: A_006 | G22: 1746 | H22: 1153 | I22: 1023 | J22: =SUM(G22:I22) -> 3922
A23: t statistic | B23: =(C21-C22)/SQRT(D21/B21+D22/B22) -> 8.303957 | F23: A_065 | G23: 10551 | H23: 3748 | I23: 4565 | J23: =SUM(G23:I23) -> 18864
A24: Welch df | B24: =(D21/B21+D22/B22)^2/((D21/B21)^2/(B21-1)+(D22/B22)^2/(B22-1)) -> 1985.7623 | F24: A_101 | G24: 9363 | H24: 4259 | I24: 4777 | J24: =SUM(G24:I24) -> 18399
A25: p-value (one-tailed) | B25: =TDIST(ABS(B23),B24,1) -> 9.195471e-17 | F25: other | G25: 13460 | H25: 17656 | I25: 15303 | J25: =SUM(G25:I25) -> 46419
A26: Decision | B26: =IF(AND(B25<0.05,B23>0),"Reject H0: weekends idle more","Fail to reject H0") -> Reject H0: weekends idle more | F26: Column total | G26: =SUM(G21:G25) -> 37838 | H26: =SUM(H21:H25) -> 27432 | I26: =SUM(I21:I25) -> 26735 | J26: =SUM(J21:J25) -> 92005
F28: Expected | G28: Shift A | H28: Shift B | I28: Shift C
F29: =F21 -> A_001 | G29: =$J21*G$26/$J$26 -> 1809.9564 | H29: =$J21*H$26/$J$26 -> 1312.1921 | I29: =$J21*I$26/$J$26 -> 1278.8515
F30: =F22 -> A_006 | G30: =$J22*G$26/$J$26 -> 1612.9627 | H30: =$J22*H$26/$J$26 -> 1169.3745 | I30: =$J22*I$26/$J$26 -> 1139.6627
F31: =F23 -> A_065 | G31: =$J23*G$26/$J$26 -> 7758.0135 | H31: =$J23*H$26/$J$26 -> 5624.447 | I31: =$J23*I$26/$J$26 -> 5481.5395
F32: =F24 -> A_101 | G32: =$J24*G$26/$J$26 -> 7566.7775 | H32: =$J24*H$26/$J$26 -> 5485.8037 | I32: =$J24*I$26/$J$26 -> 5346.4188
F33: =F25 -> other | G33: =$J25*G$26/$J$26 -> 19090.29 | H33: =$J25*H$26/$J$26 -> 13840.183 | I33: =$J25*I$26/$J$26 -> 13488.527
F34: Chi-square | G34: =SUMPRODUCT((G21:I25-G29:I33)^2/G29:I33) -> 6386.0111
F35: p-value | G35: =CHITEST(G21:I25,G29:I33) -> 0
F36: Cramer's V (effect size) | G36: =SQRT(G34/(J26*2)) -> 0.18629196
F37: Decision | G37: =IF(G35<0.05,"Reject H0 (but check effect size)","Fail to reject H0") -> Reject H0 (but check effect size)
A39: H5: Daily OEE is equal in 2020 and 2021 - tested PER MACHINE (Welch t, two-tailed). Stratify first: the pooled fleet 'decline' is a mix effect.
A40: Machine | B40: n 2020 | C40: Mean 2020 | D40: Var 2020 | E40: n 2021 | F40: Mean 2021 | G40: Var 2021 | H40: Change (pts) | I40: t | J40: df | K40: p-value | L40: Decision
A41: s_1 | B41: =COUNTIFS(Data_Daily!$A$2:$A$2407,$A41,Data_Daily!$O$2:$O$2407,2020,Data_Daily!$P$2:$P$2407,1) -> 323 | C41: =AVERAGEIFS(Data_Daily!$Q$2:$Q$2407,Data_Daily!$A$2:$A$2407,$A41,Data_Daily!$O$2:$O$2407,2020,Data_Daily!$P$2:$P$2407,1) -> 0.66657556 | D41: =SUMPRODUCT((Data_Daily!$A$2:$A$2407=$A41)*(Data_Daily!$O$2:$O$2407=2020)*(Data_Daily!$P$2:$P$2407=1)*(Data_Daily!$Q$2:$Q$2407-C41)^2)/(B41-1) -> 0.021354208 | E41: =COUNTIFS(Data_Daily!$A$2:$A$2407,$A41,Data_Daily!$O$2:$O$2407,2021,Data_Daily!$P$2:$P$2407,1) -> 298 | F41: =AVERAGEIFS(Data_Daily!$Q$2:$Q$2407,Data_Daily!$A$2:$A$2407,$A41,Data_Daily!$O$2:$O$2407,2021,Data_Daily!$P$2:$P$2407,1) -> 0.62180236 | G41: =SUMPRODUCT((Data_Daily!$A$2:$A$2407=$A41)*(Data_Daily!$O$2:$O$2407=2021)*(Data_Daily!$P$2:$P$2407=1)*(Data_Daily!$Q$2:$Q$2407-F41)^2)/(E41-1) -> 0.015927034 | H41: =(F41-C41)*100 -> -4.4773207 | I41: =(F41-C41)/SQRT(D41/B41+G41/E41) -> -4.0947551 | J41: =(D41/B41+G41/E41)^2/((D41/B41)^2/(B41-1)+(G41/E41)^2/(E41-1)) -> 616.3474 | K41: =TDIST(ABS(I41),J41,2) -> 4.7899201e-05 | L41: =IF(K41<0.05,IF(H41<0,"Significant DROP","Significant RISE"),"No change") -> Significant DROP
A42: s_2 | B42: =COUNTIFS(Data_Daily!$A$2:$A$2407,$A42,Data_Daily!$O$2:$O$2407,2020,Data_Daily!$P$2:$P$2407,1) -> 106 | C42: =AVERAGEIFS(Data_Daily!$Q$2:$Q$2407,Data_Daily!$A$2:$A$2407,$A42,Data_Daily!$O$2:$O$2407,2020,Data_Daily!$P$2:$P$2407,1) -> 0.26155741 | D42: =SUMPRODUCT((Data_Daily!$A$2:$A$2407=$A42)*(Data_Daily!$O$2:$O$2407=2020)*(Data_Daily!$P$2:$P$2407=1)*(Data_Daily!$Q$2:$Q$2407-C42)^2)/(B42-1) -> 0.016718646 | E42: =COUNTIFS(Data_Daily!$A$2:$A$2407,$A42,Data_Daily!$O$2:$O$2407,2021,Data_Daily!$P$2:$P$2407,1) -> 313 | F42: =AVERAGEIFS(Data_Daily!$Q$2:$Q$2407,Data_Daily!$A$2:$A$2407,$A42,Data_Daily!$O$2:$O$2407,2021,Data_Daily!$P$2:$P$2407,1) -> 0.35640397 | G42: =SUMPRODUCT((Data_Daily!$A$2:$A$2407=$A42)*(Data_Daily!$O$2:$O$2407=2021)*(Data_Daily!$P$2:$P$2407=1)*(Data_Daily!$Q$2:$Q$2407-F42)^2)/(E42-1) -> 0.014287451 | H42: =(F42-C42)*100 -> 9.4846554 | I42: =(F42-C42)/SQRT(D42/B42+G42/E42) -> 6.6508665 | J42: =(D42/B42+G42/E42)^2/((D42/B42)^2/(B42-1)+(G42/E42)^2/(E42-1)) -> 169.78509 | K42: =TDIST(ABS(I42),J42,2) -> 3.8702351e-10 | L42: =IF(K42<0.05,IF(H42<0,"Significant DROP","Significant RISE"),"No change") -> Significant RISE
A43: s_3 | B43: =COUNTIFS(Data_Daily!$A$2:$A$2407,$A43,Data_Daily!$O$2:$O$2407,2020,Data_Daily!$P$2:$P$2407,1) -> 68 | C43: =AVERAGEIFS(Data_Daily!$Q$2:$Q$2407,Data_Daily!$A$2:$A$2407,$A43,Data_Daily!$O$2:$O$2407,2020,Data_Daily!$P$2:$P$2407,1) -> 0.38487705 | D43: =SUMPRODUCT((Data_Daily!$A$2:$A$2407=$A43)*(Data_Daily!$O$2:$O$2407=2020)*(Data_Daily!$P$2:$P$2407=1)*(Data_Daily!$Q$2:$Q$2407-C43)^2)/(B43-1) -> 0.012588546 | E43: =COUNTIFS(Data_Daily!$A$2:$A$2407,$A43,Data_Daily!$O$2:$O$2407,2021,Data_Daily!$P$2:$P$2407,1) -> 286 | F43: =AVERAGEIFS(Data_Daily!$Q$2:$Q$2407,Data_Daily!$A$2:$A$2407,$A43,Data_Daily!$O$2:$O$2407,2021,Data_Daily!$P$2:$P$2407,1) -> 0.46682651 | G43: =SUMPRODUCT((Data_Daily!$A$2:$A$2407=$A43)*(Data_Daily!$O$2:$O$2407=2021)*(Data_Daily!$P$2:$P$2407=1)*(Data_Daily!$Q$2:$Q$2407-F43)^2)/(E43-1) -> 0.010100839 | H43: =(F43-C43)*100 -> 8.1949459 | I43: =(F43-C43)/SQRT(D43/B43+G43/E43) -> 5.5194733 | J43: =(D43/B43+G43/E43)^2/((D43/B43)^2/(B43-1)+(G43/E43)^2/(E43-1)) -> 94.196589 | K43: =TDIST(ABS(I43),J43,2) -> 2.9970978e-07 | L43: =IF(K43<0.05,IF(H43<0,"Significant DROP","Significant RISE"),"No change") -> Significant RISE
A44: s_4 | B44: =COUNTIFS(Data_Daily!$A$2:$A$2407,$A44,Data_Daily!$O$2:$O$2407,2020,Data_Daily!$P$2:$P$2407,1) -> 89 | C44: =AVERAGEIFS(Data_Daily!$Q$2:$Q$2407,Data_Daily!$A$2:$A$2407,$A44,Data_Daily!$O$2:$O$2407,2020,Data_Daily!$P$2:$P$2407,1) -> 0.44252689 | D44: =SUMPRODUCT((Data_Daily!$A$2:$A$2407=$A44)*(Data_Daily!$O$2:$O$2407=2020)*(Data_Daily!$P$2:$P$2407=1)*(Data_Daily!$Q$2:$Q$2407-C44)^2)/(B44-1) -> 0.015464749 | E44: =COUNTIFS(Data_Daily!$A$2:$A$2407,$A44,Data_Daily!$O$2:$O$2407,2021,Data_Daily!$P$2:$P$2407,1) -> 235 | F44: =AVERAGEIFS(Data_Daily!$Q$2:$Q$2407,Data_Daily!$A$2:$A$2407,$A44,Data_Daily!$O$2:$O$2407,2021,Data_Daily!$P$2:$P$2407,1) -> 0.48218518 | G44: =SUMPRODUCT((Data_Daily!$A$2:$A$2407=$A44)*(Data_Daily!$O$2:$O$2407=2021)*(Data_Daily!$P$2:$P$2407=1)*(Data_Daily!$Q$2:$Q$2407-F44)^2)/(E44-1) -> 0.01487287 | H44: =(F44-C44)*100 -> 3.965829 | I44: =(F44-C44)/SQRT(D44/B44+G44/E44) -> 2.5758109 | J44: =(D44/B44+G44/E44)^2/((D44/B44)^2/(B44-1)+(G44/E44)^2/(E44-1)) -> 155.99587 | K44: =TDIST(ABS(I44),J44,2) -> 0.01093484 | L44: =IF(K44<0.05,IF(H44<0,"Significant DROP","Significant RISE"),"No change") -> Significant RISE
A45: s_5 | B45: =COUNTIFS(Data_Daily!$A$2:$A$2407,$A45,Data_Daily!$O$2:$O$2407,2020,Data_Daily!$P$2:$P$2407,1) -> 226 | C45: =AVERAGEIFS(Data_Daily!$Q$2:$Q$2407,Data_Daily!$A$2:$A$2407,$A45,Data_Daily!$O$2:$O$2407,2020,Data_Daily!$P$2:$P$2407,1) -> 0.55056967 | D45: =SUMPRODUCT((Data_Daily!$A$2:$A$2407=$A45)*(Data_Daily!$O$2:$O$2407=2020)*(Data_Daily!$P$2:$P$2407=1)*(Data_Daily!$Q$2:$Q$2407-C45)^2)/(B45-1) -> 0.043274945 | E45: =COUNTIFS(Data_Daily!$A$2:$A$2407,$A45,Data_Daily!$O$2:$O$2407,2021,Data_Daily!$P$2:$P$2407,1) -> 209 | F45: =AVERAGEIFS(Data_Daily!$Q$2:$Q$2407,Data_Daily!$A$2:$A$2407,$A45,Data_Daily!$O$2:$O$2407,2021,Data_Daily!$P$2:$P$2407,1) -> 0.58839255 | G45: =SUMPRODUCT((Data_Daily!$A$2:$A$2407=$A45)*(Data_Daily!$O$2:$O$2407=2021)*(Data_Daily!$P$2:$P$2407=1)*(Data_Daily!$Q$2:$Q$2407-F45)^2)/(E45-1) -> 0.027121384 | H45: =(F45-C45)*100 -> 3.7822888 | I45: =(F45-C45)/SQRT(D45/B45+G45/E45) -> 2.110248 | J45: =(D45/B45+G45/E45)^2/((D45/B45)^2/(B45-1)+(G45/E45)^2/(E45-1)) -> 423.10015 | K45: =TDIST(ABS(I45),J45,2) -> 0.035423567 | L45: =IF(K45<0.05,IF(H45<0,"Significant DROP","Significant RISE"),"No change") -> Significant RISE
A48: H6: Simple regression - daily OEE vs alarm stops per run-hour (fleet, valid days)
A49: n | B49: =COUNTIF(Data_Daily!$P$2:$P$2407,1) -> 2156 | D49: Reading: stops explain only part of OEE variance (see R-squared) - idle and speed loss matter more. Do not over-claim a weak regression.
A50: mean x (stops/run-h) | B50: =AVERAGEIF(Data_Daily!$P$2:$P$2407,1,Data_Daily!$R$2:$R$2407) -> 4.7100738
A51: mean y (OEE) | B51: =AVERAGEIF(Data_Daily!$P$2:$P$2407,1,Data_Daily!$Q$2:$Q$2407) -> 0.51078718
A52: Sxy | B52: =SUMPRODUCT((Data_Daily!$P$2:$P$2407=1)*(Data_Daily!$R$2:$R$2407-B50)*(Data_Daily!$Q$2:$Q$2407-B51)) -> -588.5196
A53: Sxx | B53: =SUMPRODUCT((Data_Daily!$P$2:$P$2407=1)*(Data_Daily!$R$2:$R$2407-B50)^2) -> 34054.591
A54: Syy | B54: =SUMPRODUCT((Data_Daily!$P$2:$P$2407=1)*(Data_Daily!$Q$2:$Q$2407-B51)^2) -> 71.216742
A55: Slope (OEE per extra stop/run-h) | B55: =B52/B53 -> -0.017281652
A56: Intercept | B56: =B51-B55*B50 -> 0.59218504
A57: R-squared | B57: =B52^2/(B53*B54) -> 0.1428118
A58: t (slope) | B58: =B55/SQRT((B54-B55*B52)/(B49-2)/B53) -> -18.943787
A59: p-value | B59: =TDIST(ABS(B58),B49-2,2) -> 3.7995759e-74

Sheet I1_Solutions
A1: I1 - Solution selection matrix
A2: IMPROVE. Priority = Impact x (6 - Effort). Scores are team judgement (yellow).
A4: Root cause (from Analyze) | B4: Countermeasure | C4: Lean tool | D4: Impact 1-5 | E4: Effort 1-5 | F4: Priority | G4: Owner | H4: Wave
A5: Idle has no reason code | B5: Mandatory reason-code pop-up after 3 min idle; weekly idle Pareto | C5: Poka-Yoke (data) + visual mgmt | D5: 5 | E5: 2 | F5: =D5*(6-E5) -> 20 | G5: Shift leads + IT | H5: 1
A6: Night / weekend idle | B6: Staffing & handover standard work; pre-staged material before night shift | C6: Standard work + Kanban | D6: 5 | E6: 3 | F6: =D6*(6-E6) -> 15 | G6: Production mgr | H6: 1
A7: A_065 micro-stops (s_1) | B7: 5-day Kaizen blitz: observe 20 stops, fix trigger, CIL standard | C7: Kaizen + 5 Whys + CIL | D7: 4 | E7: 2 | F7: =D7*(6-E7) -> 16 | G7: Maint. + operators | H7: 1
A8: A_001 / A_006 long stops | B8: Error-proof the setup step, standard repair kit at the machine | C8: Poka-Yoke + 5S | D8: 3 | E8: 3 | F8: =D8*(6-E8) -> 9 | G8: Maintenance | H8: 2
A9: A_101 repeat stops (s_2/3/5) | B9: Horizontal expansion of the s_1 Kaizen method | C9: Kaizen (Yokoten) | D9: 3 | E9: 2 | F9: =D9*(6-E9) -> 12 | G9: CI engineer | H9: 2
A10: Long changeovers | B10: SMED: separate internal/external, pre-kitting, quick clamps | C10: SMED | D10: 3 | E10: 3 | F10: =D10*(6-E10) -> 9 | G10: Setup techs | H10: 2
A11: Speed loss (s_4) | B11: Rated-speed standard + CIL; review speed set-points | C11: 5S / TPM | D11: 3 | E11: 2 | F11: =D11*(6-E11) -> 12 | G11: Process eng. | H11: 2
A12: Material starvation risk | B12: Two-bin Kanban line-side; ROP/EOQ for supplier orders | C12: Kanban + inventory policy | D12: 3 | E12: 2 | F12: =D12*(6-E12) -> 12 | G12: Stores / planning | H12: 1

Sheet I2_OEE_Scenario
A1: I2 - Projected OEE bridge by Lean lever (edit the yellow reduction rates)
A2: IMPROVE. Recovered hours become run time at the current performance rate. These are PROJECTIONS - validate in the s_1 pilot.
A5: Planned production time (h) | B5: =M2_OEE!D10 -> 37596.355
A6: Run time (h) | B6: =M2_OEE!E10 -> 24182.954
A7: Performance | B7: =M2_OEE!M10 -> 0.80763044
A8: Quality | B8: =M2_OEE!N10 -> 0.99591163
A9: Idle (h) | B9: =M2_OEE!G10 -> 10265.964
A10: A_001 + A_006 downtime (h) | B10: =SUMIF(M4_Pareto!A:A,"A_001",M4_Pareto!C:C)+SUMIF(M4_Pareto!A:A,"A_006",M4_Pareto!C:C) -> 798.79671
A11: A_065 + A_101 + A_066 downtime (h) | B11: =SUMIF(M4_Pareto!A:A,"A_065",M4_Pareto!C:C)+SUMIF(M4_Pareto!A:A,"A_101",M4_Pareto!C:C)+SUMIF(M4_Pareto!A:A,"A_066",M4_Pareto!C:C) -> 1526.5401
A12: Other alarm downtime (h) | B12: =M2_OEE!F10-B10-B11 -> 822.09961
A13: Baseline OEE | B13: =B6*B7*B8/B5 -> 0.51736506
A15: Lever | B15: Lean tool | C15: Loss bucket (h) | D15: Assumed reduction | E15: Hours recovered | F15: Run time after (h) | G15: Performance after | H15: OEE after | I15: Delta (pts)
A16: Baseline | F16: =B6 -> 24182.954 | G16: =B7 -> 0.80763044 | H16: =F16*G16*$B$8/$B$5 -> 0.51736506
A17: Poka-Yoke + autonomous maintenance (A_001, A_006) | B17: Poka-Yoke / TPM | C17: =B10 -> 798.79671 | D17: 0.4 | E17: =C17*D17 -> 319.51869 | F17: =F16+E17 -> 24502.473 | G17: =G16 -> 0.80763044 | H17: =F17*G17*$B$8/$B$5 -> 0.52420077 | I17: =(H17-H16)*100 -> 0.68357159
A18: Kaizen blitz on micro-stops (A_065, A_101, A_066) | B18: Kaizen / 5 Whys | C18: =B11 -> 1526.5401 | D18: 0.3 | E18: =C18*D18 -> 457.96203 | F18: =F17+E18 -> 24960.435 | G18: =G17 -> 0.80763044 | H18: =F18*G18*$B$8/$B$5 -> 0.53399832 | I18: =(H18-H17)*100 -> 0.97975439
A19: 5S + visual management (other alarms) | B19: 5S | C19: =B12 -> 822.09961 | D19: 0.1 | E19: =C19*D19 -> 82.209961 | F19: =F18+E19 -> 25042.645 | G19: =G18 -> 0.80763044 | H19: =F19*G19*$B$8/$B$5 -> 0.5357571 | I19: =(H19-H18)*100 -> 0.17587827
A20: Idle recovery: reason codes + Kanban + night/weekend standard work | B20: Poka-Yoke (data) / Kanban / Std work | C20: =B9 -> 10265.964 | D20: 0.25 | E20: =C20*D20 -> 2566.4911 | F20: =F19+E20 -> 27609.136 | G20: =G19 -> 0.80763044 | H20: =F20*G20*$B$8/$B$5 -> 0.59066407 | I20: =(H20-H19)*100 -> 5.4906973
A21: CIL routine + rated-speed standard | B21: 5S / TPM | C21: =F20*(1-G20) -> 5311.1573 | D21: 0.2 | E21: =C21*D21 -> 1062.2315 | F21: =F20 -> 27609.136 | G21: =G20+(1-G20)*D21 -> 0.84610435 | H21: =F21*G21*$B$8/$B$5 -> 0.61880214 | I21: =(H21-H20)*100 -> 2.8138065
A22: PROJECTED OEE | H22: =H21 -> 0.61880214 | I22: =(H22-H16)*100 -> 10.143708
A25: Ideal packs per run-hour | B25: =M2_OEE!I10/M2_OEE!E10 -> 4892.6019 | D25: Blunt reading: the idle lever is worth more than all alarm levers combined. Classic 'fix the top alarm' Six Sigma would miss most of the prize.
A26: Extra good packs per year | B26: =(H22-H16)*B5*B25/Inputs!$B$8 -> 9329370.9
A27: Contribution gain (INR / year) | B27: =B26*Inputs!$B$7 -> 5597622.5
A28: Contribution gain (INR lakh / year) | B28: =B27/100000 -> 55.976225
A29: COPQ of rejects (INR / year) | B29: =(M2_OEE!J10-M2_OEE!K10)/Inputs!$B$8*Inputs!$B$7 -> 117201.6
A30: Packs lost vs ideal per year (all losses) | B30: =(1-H16)*B5*B25/Inputs!$B$8 -> 44388900

Sheet I3_SMED
A1: I3 - SMED: changeover reduction
A2: IMPROVE. Baseline from v_smed_baseline (planned stops 10 min - 4 h used as changeover proxy - ASSUMPTION).
A4: Machine | B4: Events | C4: Mean min | D4: Median min | E4: P90 min | F4: Hours | G4: Events / year | H4: Target mean min | I4: Hours released / year
A5: s_1 | B5: 1411 | C5: 36.621765 | D5: 24.845517 | E5: 58.701767 | F5: 861.22184 | G5: =B5/Inputs!$B$8 -> 705.5 | H5: =C5*(1-Inputs!$B$18) -> 21.973059 | I5: =F5/Inputs!$B$8*Inputs!$B$18 -> 172.24437
A6: s_2 | B6: 1489 | C6: 52.552337 | D6: 50.528217 | E6: 72.260587 | F6: 1304.1738 | G6: =B6/Inputs!$B$8 -> 744.5 | H6: =C6*(1-Inputs!$B$18) -> 31.531402 | I6: =F6/Inputs!$B$8*Inputs!$B$18 -> 260.83476
A7: s_3 | B7: 823 | C7: 43.900472 | D7: 15 | E7: 109.82877 | F7: 602.16815 | G7: =B7/Inputs!$B$8 -> 411.5 | H7: =C7*(1-Inputs!$B$18) -> 26.340283 | I7: =F7/Inputs!$B$8*Inputs!$B$18 -> 120.43363
A8: s_4 | B8: 642 | C8: 68.052163 | D8: 50.139167 | E8: 162.89771 | F8: 728.15814 | G8: =B8/Inputs!$B$8 -> 321 | H8: =C8*(1-Inputs!$B$18) -> 40.831298 | I8: =F8/Inputs!$B$8*Inputs!$B$18 -> 145.63163
A9: s_5 | B9: 1604 | C9: 60.395896 | D9: 38.977408 | E9: 166.76665 | F9: 1614.5836 | G9: =B9/Inputs!$B$8 -> 802 | H9: =C9*(1-Inputs!$B$18) -> 36.237538 | I9: =F9/Inputs!$B$8*Inputs!$B$18 -> 322.91672
A10: Fleet | B10: =SUM(B5:B9) -> 5969 | C10: =SUMPRODUCT(B5:B9,C5:C9)/B10 -> 51.368459 | F10: =SUM(F5:F9) -> 5110.3056 | I10: =SUM(I5:I9) -> 1022.0611
A12: SMED study template (TEMPLATE EXAMPLE - replace with a timed video study of one real changeover)
A13: # | B13: Element | C13: Current min | D13: Internal / External (now) | E13: Can it be external? | F13: Improvement idea | G13: Future min | H13: Future type
A14: 1 | B14: Stop machine, clear line | C14: 3 | D14: Internal | E14: No | F14: Standard stop sequence | G14: 2 | H14: Internal
A15: 2 | B15: Fetch new film reel / blanks from store | C15: 8 | D15: Internal | E15: Yes | F15: Pre-kit on trolley before stop (Kanban) | G15: 0 | H15: External
A16: 3 | B16: Fetch tools and change parts | C16: 6 | D16: Internal | E16: Yes | F16: Shadow board at machine (5S) | G16: 0 | H16: External
A17: 4 | B17: Remove old format parts | C17: 7 | D17: Internal | E17: No | F17: Quick-release clamps | G17: 4 | H17: Internal
A18: 5 | B18: Fit new format parts | C18: 8 | D18: Internal | E18: No | F18: Colour-coded, keyed parts (Poka-Yoke) | G18: 5 | H18: Internal
A19: 6 | B19: Adjust guides by trial and error | C19: 10 | D19: Internal | E19: No | F19: Fixed-position stops, no adjustment | G19: 3 | H19: Internal
A20: 7 | B20: First-off quality check | C20: 4 | D20: Internal | E20: No | F20: Go/no-go gauge | G20: 3 | H20: Internal
A21: 8 | B21: Paperwork / log entry | C21: 3 | D21: Internal | E21: Yes | F21: Do while running | G21: 0 | H21: External
B22: Total internal (machine stopped) minutes | C22: =SUMIF(D14:D21,"Internal",C14:C21) -> 49 | G22: =SUMIF(H14:H21,"Internal",G14:G21) -> 17
B23: Reduction | G23: =1-G22/C22 -> 0.65306122

Sheet I4_PokaYoke
A1: I4 - Poka-Yoke (error-proofing) plan
A2: IMPROVE. Alarm codes are anonymised, so devices are proposals to validate with maintenance.
A4: Failure mode / error | B4: Poka-Yoke device | C4: Type | D4: Function | E4: Verification
A5: Idle with no reason (data error) | B5: HMI forces a reason-code choice after 3 min idle; cannot restart without it | C5: Motion-step | D5: Control (prevent) | E5: % idle minutes coded >= 95%
A6: A_001 / A_006 long stops | B6: Keyed / colour-coded change parts that fit only one way | C6: Contact | D6: Control | E6: Stop count per 1,000 run-h
A7: A_065 jam at infeed (hyp.) | B7: Photo-eye detects mis-fed blank and diverts it before the jam | C7: Contact (sensor) | D7: Warning + divert | E7: A_065 stops per run-h
A8: Wrong material staged | B8: Barcode scan of film / blank lot vs work order before start | C8: Fixed-value | D8: Control | E8: Wrong-material incidents = 0
A9: Changeover step skipped | B9: Checklist on HMI with interlock until all steps confirmed | C9: Motion-step | D9: Control | E9: First-off pass rate
A10: Speed set below rated | B10: Speed set-point locked to recipe; override needs supervisor PIN | C10: Fixed-value | D10: Control | E10: Performance rate

Sheet I5_5S_Audit
A1: I5 - 5S audit (score 0-4, yellow cells)
A2: IMPROVE / CONTROL. Audit weekly in the pilot, monthly after.
A4: S | B4: Audit question | C4: Score (0-4)
A5: Sort | B5: Only items needed for the current format are at the machine | C5: 3
A6: Sort | B6: Red-tag area exists and is cleared weekly | C6: 2
A7: Set in order | B7: Shadow board for changeover tools; every tool has a home | C7: 2
A8: Set in order | B8: Kanban bins labelled with qty and location | C8: 1
A9: Shine | B9: Cleaning = inspection: CIL checklist done every shift | C9: 1
A10: Shine | B10: Sources of dust / glue / film scrap identified and contained | C10: 2
A11: Standardise | B11: One-point lessons posted for top 3 alarms | C11: 1
A12: Standardise | B12: Changeover standard (SMED) displayed and followed | C12: 1
A13: Sustain | B13: Audit done on schedule with actions tracked | C13: 2
A14: Sustain | B14: Shift handover includes OEE and idle reasons | C14: 1
A16: S | B16: Score %
A17: Sort | B17: =SUMIF($A$5:$A$14,A17,$C$5:$C$14)/(COUNTIF($A$5:$A$14,A17)*4) -> 0.625
A18: Set in order | B18: =SUMIF($A$5:$A$14,A18,$C$5:$C$14)/(COUNTIF($A$5:$A$14,A18)*4) -> 0.375
A19: Shine | B19: =SUMIF($A$5:$A$14,A19,$C$5:$C$14)/(COUNTIF($A$5:$A$14,A19)*4) -> 0.375
A20: Standardise | B20: =SUMIF($A$5:$A$14,A20,$C$5:$C$14)/(COUNTIF($A$5:$A$14,A20)*4) -> 0.25
A21: Sustain | B21: =SUMIF($A$5:$A$14,A21,$C$5:$C$14)/(COUNTIF($A$5:$A$14,A21)*4) -> 0.375
A22: Overall 5S score | B22: =SUM(C5:C14)/(COUNT(C5:C14)*4) -> 0.4
A23: Example scores shown - replace with your own audit.

Sheet I6_Kaizen
A1: I6 - Kaizen event (5-day blitz on A_065, s_1) + PDCA tracker
A2: IMPROVE.
A4: Day | B4: Activity | C4: Output
A5: Day 1 | B5: Train team; review Pareto/FMEA; walk the line; set target (-30% A_065 hours) | C5: Kaizen charter
A6: Day 2 | B6: Observe and video 20+ A_065 stops; 5 Whys on each; tag triggers | C6: Cause list with evidence
A7: Day 3 | B7: Try fixes on the machine (adjust, clean, guide, sensor); SMED on recovery | C7: Tested countermeasures
A8: Day 4 | B8: Standardise: one-point lessons, CIL sheet, Poka-Yoke proposals | C8: Standard work
A9: Day 5 | B9: Report-out; compare stops/run-h before vs after on the X-bar/R chart | C9: 30-day action list
A11: PDCA | B11: Action | C11: Owner | D11: Due | E11: Status | F11: Metric before | G11: Metric after
A12: Plan | B12: Baseline A_065 stops/run-h on s_1 | C12: CI eng. | D12: Wk 9 | E12: Open | F12: =SUMIF(M4_Pareto!A:A,"A_065",M4_Pareto!B:B)/M2_OEE!E5 -> 2.0403343
A13: Do | B13: Kaizen countermeasures implemented | C13: Maint. | D13: Wk 10 | E13: Open
A14: Check | B14: 30-day X-bar/R review, t-test before vs after | C14: BB/GB | D14: Wk 14 | E14: Open
A15: Act | B15: Standardise + roll out to s_2/s_3/s_5 (A_101) | C15: Prod. mgr | D15: Wk 16 | E15: Open

Sheet I7_Kanban
A1: I7 - Kanban sizing for line-side packaging material
A2: IMPROVE. N = ROUNDUP( D x L x (1 + alpha) / C ).
A4: Machine | B4: Avg draw (blanks/h, planned time) | C4: Rated draw (blanks/h) | D4: Kanbans - average | E4: Kanbans - peak (rated speed) | F4: Max line-side stock | G4: Hours of cover at avg draw
A5: s_1 | B5: =M2_OEE!J5/M2_OEE!D5 -> 2627.7969 | C5: =M2_OEE!I5/M2_OEE!E5 -> 4011.2862 | D5: =ROUNDUP(B5*Inputs!$B$16*(1+Inputs!$B$17)/Inputs!$B$15,0) -> 13 | E5: =ROUNDUP(C5*Inputs!$B$16*(1+Inputs!$B$17)/Inputs!$B$15,0) -> 19 | F5: =E5*Inputs!$B$15 -> 38000 | G5: =F5/B5 -> 14.460783
A6: s_2 | B6: =M2_OEE!J6/M2_OEE!D6 -> 2002.5808 | C6: =M2_OEE!I6/M2_OEE!E6 -> 6179.9289 | D6: =ROUNDUP(B6*Inputs!$B$16*(1+Inputs!$B$17)/Inputs!$B$15,0) -> 10 | E6: =ROUNDUP(C6*Inputs!$B$16*(1+Inputs!$B$17)/Inputs!$B$15,0) -> 29 | F6: =E6*Inputs!$B$15 -> 58000 | G6: =F6/B6 -> 28.962626
A7: s_3 | B7: =M2_OEE!J7/M2_OEE!D7 -> 1764.3638 | C7: =M2_OEE!I7/M2_OEE!E7 -> 3985.7305 | D7: =ROUNDUP(B7*Inputs!$B$16*(1+Inputs!$B$17)/Inputs!$B$15,0) -> 9 | E7: =ROUNDUP(C7*Inputs!$B$16*(1+Inputs!$B$17)/Inputs!$B$15,0) -> 19 | F7: =E7*Inputs!$B$15 -> 38000 | G7: =F7/B7 -> 21.537508
A8: s_4 | B8: =M2_OEE!J8/M2_OEE!D8 -> 2504.7211 | C8: =M2_OEE!I8/M2_OEE!E8 -> 5551.3703 | D8: =ROUNDUP(B8*Inputs!$B$16*(1+Inputs!$B$17)/Inputs!$B$15,0) -> 12 | E8: =ROUNDUP(C8*Inputs!$B$16*(1+Inputs!$B$17)/Inputs!$B$15,0) -> 26 | F8: =E8*Inputs!$B$15 -> 52000 | G8: =F8/B8 -> 20.760795
A9: s_5 | B9: =M2_OEE!J9/M2_OEE!D9 -> 3317.473 | C9: =M2_OEE!I9/M2_OEE!E9 -> 5982.1812 | D9: =ROUNDUP(B9*Inputs!$B$16*(1+Inputs!$B$17)/Inputs!$B$15,0) -> 16 | E9: =ROUNDUP(C9*Inputs!$B$16*(1+Inputs!$B$17)/Inputs!$B$15,0) -> 28 | F9: =E9*Inputs!$B$15 -> 56000 | G9: =F9/B9 -> 16.880318
A11: Size on the PEAK (rated-speed) draw: sizing on the average starves the machine whenever it runs well.

Sheet I8_Inventory
A1: I8 - Inventory optimisation: Safety Stock, Reorder Point, EOQ (service-level based)
A2: IMPROVE. Daily demand stats from v_inventory_policy (Phase I = 2020). SS = z x SQRT(L x sd_d^2 + d^2 x sd_L^2); ROP = d x L + SS; EOQ = SQRT(2DS/H).
A4: Machine | B4: Mean daily demand | C4: SD daily demand | D4: Training days | E4: z | F4: Sigma LTD | G4: Safety stock | H4: Reorder point | I4: Annual demand | J4: Holding cost / unit / yr | K4: EOQ | L4: Orders / year | M4: Avg inventory | N4: Days of cover | O4: Total annual cost (INR)
A5: s_1 | B5: 42412.044 | C5: 26514.723 | D5: 366 | E5: =NORMSINV(Inputs!$B$14) -> 2.0537489 | F5: =SQRT(Inputs!$B$12*C5^2+B5^2*Inputs!$B$13^2) -> 94702.017 | G5: =E5*F5 -> 194494.16 | H5: =B5*Inputs!$B$12+G5 -> 491378.47 | I5: =B5*365 -> 15480396 | J5: =Inputs!$B$9*Inputs!$B$11 -> 0.96 | K5: =SQRT(2*I5*Inputs!$B$10/J5) -> 439891.97 | L5: =I5/K5 -> 35.191358 | M5: =K5/2+G5 -> 414440.15 | N5: =M5/B5 -> 9.7717562 | O5: =J5*M5+L5*Inputs!$B$10 -> 609010.69
A6: s_2 | B6: 6980.12 | C6: 7969.6386 | D6: 200 | E6: =NORMSINV(Inputs!$B$14) -> 2.0537489 | F6: =SQRT(Inputs!$B$12*C6^2+B6^2*Inputs!$B$13^2) -> 23542.104 | G6: =E6*F6 -> 48349.57 | H6: =B6*Inputs!$B$12+G6 -> 97210.41 | I6: =B6*365 -> 2547743.8 | J6: =Inputs!$B$9*Inputs!$B$11 -> 0.96 | K6: =SQRT(2*I6*Inputs!$B$10/J6) -> 178456.71 | L6: =I6/K6 -> 14.276537 | M6: =K6/2+G6 -> 137577.92 | N6: =M6/B6 -> 19.709966 | O6: =J6*M6+L6*Inputs!$B$10 -> 217734.03
A7: s_3 | B7: 24066.988 | C7: 13519.967 | D7: 86 | E7: =NORMSINV(Inputs!$B$14) -> 2.0537489 | F7: =SQRT(Inputs!$B$12*C7^2+B7^2*Inputs!$B$13^2) -> 50820.973 | G7: =E7*F7 -> 104373.52 | H7: =B7*Inputs!$B$12+G7 -> 272842.44 | I7: =B7*365 -> 8784450.8 | J7: =Inputs!$B$9*Inputs!$B$11 -> 0.96 | K7: =SQRT(2*I7*Inputs!$B$10/J7) -> 331369.33 | L7: =I7/K7 -> 26.509547 | M7: =K7/2+G7 -> 270058.18 | N7: =M7/B7 -> 11.221104 | O7: =J7*M7+L7*Inputs!$B$10 -> 418313.14
A8: s_4 | B8: 11152.902 | C8: 19641.018 | D8: 366 | E8: =NORMSINV(Inputs!$B$14) -> 2.0537489 | F8: =SQRT(Inputs!$B$12*C8^2+B8^2*Inputs!$B$13^2) -> 54591.743 | G8: =E8*F8 -> 112117.73 | H8: =B8*Inputs!$B$12+G8 -> 190188.04 | I8: =B8*365 -> 4070809.1 | J8: =Inputs!$B$9*Inputs!$B$11 -> 0.96 | K8: =SQRT(2*I8*Inputs!$B$10/J8) -> 225577.29 | L8: =I8/K8 -> 18.046183 | M8: =K8/2+G8 -> 224906.38 | N8: =M8/B8 -> 20.165728 | O8: =J8*M8+L8*Inputs!$B$10 -> 324187.22
A9: s_5 | B9: 39618.437 | C9: 37903.051 | D9: 355 | E9: =NORMSINV(Inputs!$B$14) -> 2.0537489 | F9: =SQRT(Inputs!$B$12*C9^2+B9^2*Inputs!$B$13^2) -> 116568.16 | G9: =E9*F9 -> 239401.72 | H9: =B9*Inputs!$B$12+G9 -> 516730.78 | I9: =B9*365 -> 14460729 | J9: =Inputs!$B$9*Inputs!$B$11 -> 0.96 | K9: =SQRT(2*I9*Inputs!$B$10/J9) -> 425157.76 | L9: =I9/K9 -> 34.01262 | M9: =K9/2+G9 -> 451980.6 | N9: =M9/B9 -> 11.40834 | O9: =J9*M9+L9*Inputs!$B$10 -> 637977.1
A12: Safety stock by service level (sensitivity)
A13: Service level | B13: s_1 | C13: s_2 | D13: s_3 | E13: s_4 | F13: s_5
A14: 0.9 | B14: =NORMSINV($A14)*$F$5 -> 121365.52 | C14: =NORMSINV($A14)*$F$6 -> 30170.42 | D14: =NORMSINV($A14)*$F$7 -> 65129.698 | E14: =NORMSINV($A14)*$F$8 -> 69962.133 | F14: =NORMSINV($A14)*$F$9 -> 149388.1
A15: 0.95 | B15: =NORMSINV($A15)*$F$5 -> 155770.96 | C15: =NORMSINV($A15)*$F$6 -> 38723.315 | D15: =NORMSINV($A15)*$F$7 -> 83593.062 | E15: =NORMSINV($A15)*$F$8 -> 89795.426 | F15: =NORMSINV($A15)*$F$9 -> 191737.55
A16: 0.98 | B16: =NORMSINV($A16)*$F$5 -> 194494.16 | C16: =NORMSINV($A16)*$F$6 -> 48349.57 | D16: =NORMSINV($A16)*$F$7 -> 104373.52 | E16: =NORMSINV($A16)*$F$8 -> 112117.73 | F16: =NORMSINV($A16)*$F$9 -> 239401.72
A17: 0.99 | B17: =NORMSINV($A17)*$F$5 -> 220309.83 | C17: =NORMSINV($A17)*$F$6 -> 54767.123 | D17: =NORMSINV($A17)*$F$7 -> 118227.26 | E17: =NORMSINV($A17)*$F$8 -> 126999.38 | F17: =NORMSINV($A17)*$F$9 -> 271178.08
A19: Out-of-sample backtest of the (ROP, EOQ) policy on real 2021 consumption (Python simulation, 100 runs, random lead times)
A20: Machine | B20: Target CSL | C20: Static policy CSL | D20: Static fill rate | E20: Adaptive CSL (monthly re-fit) | F20: Adaptive fill rate | G20: 2020 mean demand | H20: 2021 mean demand
A21: s_1 | B21: 0.98 | C21: 0.94950817 | D21: 0.99562116 | E21: 0.94479832 | F21: 0.99423226 | G21: 42412.044 | H21: 43188.559
A22: s_2 | B22: 0.98 | C22: 0.27106073 | D22: 0.83830132 | E22: 0.93535 | F22: 0.99536422 | G22: 6980.12 | H22: 19017.6
A23: s_3 | B23: 0.98 | C23: 0.81618842 | D23: 0.98335459 | E23: 0.90658065 | F23: 0.99120432 | G23: 24066.988 | H23: 26859.022
A24: s_4 | B24: 0.98 | C24: 0.14948312 | D24: 0.74293099 | E24: 0.81347907 | F24: 0.86859057 | G24: 11152.902 | H24: 30724.267
A25: s_5 | B25: 0.98 | C25: 0.76615619 | D25: 0.95528839 | E25: 0.7959972 | F25: 0.9359884 | G25: 39618.437 | H25: 39736.926
A27: Reading: a policy fitted once breaks when demand shifts (s_2, s_4 volume ~2.7x in 2021). Control-phase rule: re-fit ROP/EOQ monthly and use the larger of normal and empirical safety stock.
A30: Spare kits for high-risk failure modes (ASSUMPTION: a stop >= 30 min consumes one kit). Poisson demand -> exact reorder point.
A31: Failure mode | B31: Kit events / week | C31: Lead time (weeks) | D31: Mean lead-time demand | E31: Reorder point (Poisson) | F31: Achieved service level | G31: Safety stock | H31: EOQ (kits) | K31: P(X<=0) | L31: P(X<=1) | M31: P(X<=2) | N31: P(X<=3) | O31: P(X<=4) | P31: P(X<=5) | Q31: P(X<=6) | R31: P(X<=7) | S31: P(X<=8) | T31: P(X<=9) | U31: P(X<=10) | V31: P(X<=11) | W31: P(X<=12) | X31: P(X<=13) | Y31: P(X<=14) | Z31: P(X<=15)
A32: A_065 | B32: 1.5321477 | C32: =Inputs!$B$19/7 -> 3 | D32: =B32*C32 -> 4.5964432 | E32: =COUNTIF(K32:Z32,"<"&Inputs!$B$20) -> 8 | F32: =POISSON(E32,D32,TRUE()) -> 0.95510557 | G32: =E32-D32 -> 3.4035568 | H32: =ROUND(SQRT(2*B32*52*Inputs!$B$22/(Inputs!$B$21*Inputs!$B$23)),0) -> 11 | K32: =POISSON(0,$D32,TRUE()) -> 0.010087651 | L32: =POISSON(1,$D32,TRUE()) -> 0.056454969 | M32: =POISSON(2,$D32,TRUE()) -> 0.16301734 | N32: =POISSON(3,$D32,TRUE()) -> 0.32628664 | O32: =POISSON(4,$D32,TRUE()) -> 0.51390115 | P32: =POISSON(5,$D32,TRUE()) -> 0.68637304 | Q32: =POISSON(6,$D32,TRUE()) -> 0.81849925 | R32: =POISSON(7,$D32,TRUE()) -> 0.90525791 | S32: =POISSON(8,$D32,TRUE()) -> 0.95510557 | T32: =POISSON(9,$D32,TRUE()) -> 0.98056356 | U32: =POISSON(10,$D32,TRUE()) -> 0.99226518 | V32: =POISSON(11,$D32,TRUE()) -> 0.9971548 | W32: =POISSON(12,$D32,TRUE()) -> 0.99902771 | X32: =POISSON(13,$D32,TRUE()) -> 0.99968991 | Y32: =POISSON(14,$D32,TRUE()) -> 0.99990733 | Z32: =POISSON(15,$D32,TRUE()) -> 0.99997395
A33: A_001 | B33: 0.93844049 | C33: =Inputs!$B$19/7 -> 3 | D33: =B33*C33 -> 2.8153215 | E33: =COUNTIF(K33:Z33,"<"&Inputs!$B$20) -> 6 | F33: =POISSON(E33,D33,TRUE()) -> 0.97496033 | G33: =E33-D33 -> 3.1846785 | H33: =ROUND(SQRT(2*B33*52*Inputs!$B$22/(Inputs!$B$21*Inputs!$B$23)),0) -> 8 | K33: =POISSON(0,$D33,TRUE()) -> 0.059885464 | L33: =POISSON(1,$D33,TRUE()) -> 0.2284823 | M33: =POISSON(2,$D33,TRUE()) -> 0.46580944 | N33: =POISSON(3,$D33,TRUE()) -> 0.68852684 | O33: =POISSON(4,$D33,TRUE()) -> 0.84528211 | P33: =POISSON(5,$D33,TRUE()) -> 0.9335454 | Q33: =POISSON(6,$D33,TRUE()) -> 0.97496033 | R33: =POISSON(7,$D33,TRUE()) -> 0.99161695 | S33: =POISSON(8,$D33,TRUE()) -> 0.99747866 | T33: =POISSON(9,$D33,TRUE()) -> 0.99931229 | U33: =POISSON(10,$D33,TRUE()) -> 0.99982851 | V33: =POISSON(11,$D33,TRUE()) -> 0.99996063 | W33: =POISSON(12,$D33,TRUE()) -> 0.99999163 | X33: =POISSON(13,$D33,TRUE()) -> 0.99999834 | Y33: =POISSON(14,$D33,TRUE()) -> 0.99999969 | Z33: =POISSON(15,$D33,TRUE()) -> 0.99999995
A34: A_006 | B34: 0.85225718 | C34: =Inputs!$B$19/7 -> 3 | D34: =B34*C34 -> 2.5567715 | E34: =COUNTIF(K34:Z34,"<"&Inputs!$B$20) -> 5 | F34: =POISSON(E34,D34,TRUE()) -> 0.95407853 | G34: =E34-D34 -> 2.4432285 | H34: =ROUND(SQRT(2*B34*52*Inputs!$B$22/(Inputs!$B$21*Inputs!$B$23)),0) -> 8 | K34: =POISSON(0,$D34,TRUE()) -> 0.077554719 | L34: =POISSON(1,$D34,TRUE()) -> 0.27584442 | M34: =POISSON(2,$D34,TRUE()) -> 0.52933514 | N34: =POISSON(3,$D34,TRUE()) -> 0.74537444 | O34: =POISSON(4,$D34,TRUE()) -> 0.88346522 | P34: =POISSON(5,$D34,TRUE()) -> 0.95407853 | Q34: =POISSON(6,$D34,TRUE()) -> 0.98416889 | R34: =POISSON(7,$D34,TRUE()) -> 0.99515948 | S34: =POISSON(8,$D34,TRUE()) -> 0.99867203 | T34: =POISSON(9,$D34,TRUE()) -> 0.9996699 | U34: =POISSON(10,$D34,TRUE()) -> 0.99992503 | V34: =POISSON(11,$D34,TRUE()) -> 0.99998433 | W34: =POISSON(12,$D34,TRUE()) -> 0.99999697 | X34: =POISSON(13,$D34,TRUE()) -> 0.99999945 | Y34: =POISSON(14,$D34,TRUE()) -> 0.99999991 | Z34: =POISSON(15,$D34,TRUE()) -> 0.99999999

Sheet C1_XbarR_s1
A1: C1 - X-bar & R chart: daily OEE of pilot machine s_1 (subgroup = 3 shifts of one production day)
A2: CONTROL. Data from v_xbar_r_subgroups. Phase I (2020) sets limits; points with assignable causes are removed once; Phase II (2021) is monitored.
D3: Pass 1: all Phase I | G3: Revised limits (assignable causes removed) | J3: Phase II (2021) monitoring | S3: n | T3: A2 | U3: D3 | V3: D4 | W3: d2
A4: Subgroup size n | B4: 3 | D4: X-double-bar | E4: =AVERAGEIF($E$16:$E$494,"Phase I",$F$16:$F$494) -> 0.6144601 | G4: X-double-bar (CL) | H4: =AVERAGEIFS($F$16:$F$494,$E$16:$E$494,"Phase I",$H$16:$H$494,0) -> 0.6727815 | J4: Subgroups | K4: =COUNTIF($E$16:$E$494,"Phase II") -> 224 | S4: 2 | T4: 1.88 | U4: 0 | V4: 3.267 | W4: 1.128
A5: A2 | B5: =INDEX($T$4:$T$12,MATCH(B4,$S$4:$S$12,0)) -> 1.023 | D5: R-bar | E5: =AVERAGEIF($E$16:$E$494,"Phase I",$G$16:$G$494) -> 0.32710943 | G5: R-bar | H5: =AVERAGEIFS($G$16:$G$494,$E$16:$E$494,"Phase I",$H$16:$H$494,0) -> 0.27991763 | J5: X beyond limits | K5: =COUNTIFS($E$16:$E$494,"Phase II",$N$16:$N$494,1) -> 8 | S5: 3 | T5: 1.023 | U5: 0 | V5: 2.574 | W5: 1.693
A6: D3 | B6: =INDEX($U$4:$U$12,MATCH(B4,$S$4:$S$12,0)) -> 0 | D6: UCL X | E6: =E4+B5*E5 -> 0.94909305 | G6: UCL X | H6: =H4+B5*H5 -> 0.95913723 | J6: R beyond UCL | K6: =COUNTIFS($E$16:$E$494,"Phase II",$O$16:$O$494,1) -> 6 | S6: 4 | T6: 0.729 | U6: 0 | V6: 2.282 | W6: 2.059
A7: D4 | B7: =INDEX($V$4:$V$12,MATCH(B4,$S$4:$S$12,0)) -> 2.574 | D7: LCL X | E7: =E4-B5*E5 -> 0.27982716 | G7: LCL X | H7: =H4-B5*H5 -> 0.38642576 | J7: 8-in-a-row one side | K7: =COUNTIFS($E$16:$E$494,"Phase II",$Q$16:$Q$494,1) -> 18 | S7: 5 | T7: 0.577 | U7: 0 | V7: 2.114 | W7: 2.326
A8: d2 | B8: =INDEX($W$4:$W$12,MATCH(B4,$S$4:$S$12,0)) -> 1.693 | D8: UCL R | E8: =B7*E5 -> 0.84197966 | G8: UCL R | H8: =B7*H5 -> 0.72050798 | J8: Mean X-bar Phase II | K8: =AVERAGEIF($E$16:$E$494,"Phase II",$F$16:$F$494) -> 0.6269309 | S8: 6 | T8: 0.483 | U8: 0 | V8: 2.004 | W8: 2.534
G9: LCL R | H9: =B6*H5 -> 0 | J9: Mean R Phase II | K9: =AVERAGEIF($E$16:$E$494,"Phase II",$G$16:$G$494) -> 0.29275751 | S9: 7 | T9: 0.419 | U9: 0.076 | V9: 1.924 | W9: 2.704
G10: Sigma within = R-bar / d2 | H10: =H5/B8 -> 0.16533823 | J10: Shift in mean (pts) | K10: =(K8-H4)*100 -> -4.5850598 | S10: 8 | T10: 0.373 | U10: 0.136 | V10: 1.864 | W10: 2.847
G11: Phase I subgroups kept | H11: =COUNTIFS($E$16:$E$494,"Phase I",$H$16:$H$494,0) -> 216 | S11: 9 | T11: 0.337 | U11: 0.184 | V11: 1.816 | W11: 2.97
G12: Phase I subgroups removed | H12: =COUNTIFS($E$16:$E$494,"Phase I",$H$16:$H$494,1) -> 39 | S12: 10 | T12: 0.308 | U12: 0.223 | V12: 1.777 | W12: 3.078
A15: Production day | B15: OEE shift A | C15: OEE shift B | D15: OEE shift C | E15: Phase | F15: X-bar | G15: R | H15: Pass-1 flag (1 = removed) | I15: CL | J15: UCL X | K15: LCL X | L15: R-bar | M15: UCL R | N15: X out | O15: R out | P15: Side | Q15: 8-in-a-row
A16: 43832 | B16: 0.67518347 | C16: 0.68665093 | D16: 0.57545799 | E16: Phase I | F16: =AVERAGE(B16:D16) -> 0.64576413 | G16: =MAX(B16:D16)-MIN(B16:D16) -> 0.11119294 | H16: =IF(AND(E16="Phase I",OR(F16>$E$6,F16<$E$7,G16>$E$8)),1,0) -> 0 | I16: =$H$4 -> 0.6727815 | J16: =$H$6 -> 0.95913723 | K16: =$H$7 -> 0.38642576 | L16: =$H$5 -> 0.27991763 | M16: =$H$8 -> 0.72050798 | N16: =IF(OR(F16>J16,F16<K16),1,0) -> 0 | O16: =IF(G16>M16,1,0) -> 0 | P16: =SIGN(F16-I16) -> -1 | Q16: 0
A17: 43833 | B17: 0.52363197 | C17: 0.75379397 | D17: 0.6703997 | E17: Phase I | F17: =AVERAGE(B17:D17) -> 0.64927521 | G17: =MAX(B17:D17)-MIN(B17:D17) -> 0.230162 | H17: =IF(AND(E17="Phase I",OR(F17>$E$6,F17<$E$7,G17>$E$8)),1,0) -> 0 | I17: =$H$4 -> 0.6727815 | J17: =$H$6 -> 0.95913723 | K17: =$H$7 -> 0.38642576 | L17: =$H$5 -> 0.27991763 | M17: =$H$8 -> 0.72050798 | N17: =IF(OR(F17>J17,F17<K17),1,0) -> 0 | O17: =IF(G17>M17,1,0) -> 0 | P17: =SIGN(F17-I17) -> -1 | Q17: 0
A18: 43836 | B18: 0 | C18: 0 | D18: 0.70297191 | E18: Phase I | F18: =AVERAGE(B18:D18) -> 0.23432397 | G18: =MAX(B18:D18)-MIN(B18:D18) -> 0.70297191 | H18: =IF(AND(E18="Phase I",OR(F18>$E$6,F18<$E$7,G18>$E$8)),1,0) -> 1 | I18: =$H$4 -> 0.6727815 | J18: =$H$6 -> 0.95913723 | K18: =$H$7 -> 0.38642576 | L18: =$H$5 -> 0.27991763 | M18: =$H$8 -> 0.72050798 | N18: =IF(OR(F18>J18,F18<K18),1,0) -> 1 | O18: =IF(G18>M18,1,0) -> 0 | P18: =SIGN(F18-I18) -> -1 | Q18: 0
A19: 43837 | B19: 0.74108522 | C19: 0.7997053 | D19: 0.55756721 | E19: Phase I | F19: =AVERAGE(B19:D19) -> 0.69945258 | G19: =MAX(B19:D19)-MIN(B19:D19) -> 0.24213808 | H19: =IF(AND(E19="Phase I",OR(F19>$E$6,F19<$E$7,G19>$E$8)),1,0) -> 0 | I19: =$H$4 -> 0.6727815 | J19: =$H$6 -> 0.95913723 | K19: =$H$7 -> 0.38642576 | L19: =$H$5 -> 0.27991763 | M19: =$H$8 -> 0.72050798 | N19: =IF(OR(F19>J19,F19<K19),1,0) -> 0 | O19: =IF(G19>M19,1,0) -> 0 | P19: =SIGN(F19-I19) -> 1 | Q19: 0
A20: 43838 | B20: 0.72783141 | C20: 0.7140336 | D20: 0.95844146 | E20: Phase I | F20: =AVERAGE(B20:D20) -> 0.80010216 | G20: =MAX(B20:D20)-MIN(B20:D20) -> 0.24440786 | H20: =IF(AND(E20="Phase I",OR(F20>$E$6,F20<$E$7,G20>$E$8)),1,0) -> 0 | I20: =$H$4 -> 0.6727815 | J20: =$H$6 -> 0.95913723 | K20: =$H$7 -> 0.38642576 | L20: =$H$5 -> 0.27991763 | M20: =$H$8 -> 0.72050798 | N20: =IF(OR(F20>J20,F20<K20),1,0) -> 0 | O20: =IF(G20>M20,1,0) -> 0 | P20: =SIGN(F20-I20) -> 1 | Q20: 0
A21: 43839 | B21: 0.69190713 | C21: 0.6649772 | D21: 0.77831179 | E21: Phase I | F21: =AVERAGE(B21:D21) -> 0.71173204 | G21: =MAX(B21:D21)-MIN(B21:D21) -> 0.1133346 | H21: =IF(AND(E21="Phase I",OR(F21>$E$6,F21<$E$7,G21>$E$8)),1,0) -> 0 | I21: =$H$4 -> 0.6727815 | J21: =$H$6 -> 0.95913723 | K21: =$H$7 -> 0.38642576 | L21: =$H$5 -> 0.27991763 | M21: =$H$8 -> 0.72050798 | N21: =IF(OR(F21>J21,F21<K21),1,0) -> 0 | O21: =IF(G21>M21,1,0) -> 0 | P21: =SIGN(F21-I21) -> 1 | Q21: 0
A22: 43840 | B22: 0.71483084 | C22: 0.73972723 | D22: 0.68978717 | E22: Phase I | F22: =AVERAGE(B22:D22) -> 0.71478175 | G22: =MAX(B22:D22)-MIN(B22:D22) -> 0.049940063 | H22: =IF(AND(E22="Phase I",OR(F22>$E$6,F22<$E$7,G22>$E$8)),1,0) -> 0 | I22: =$H$4 -> 0.6727815 | J22: =$H$6 -> 0.95913723 | K22: =$H$7 -> 0.38642576 | L22: =$H$5 -> 0.27991763 | M22: =$H$8 -> 0.72050798 | N22: =IF(OR(F22>J22,F22<K22),1,0) -> 0 | O22: =IF(G22>M22,1,0) -> 0 | P22: =SIGN(F22-I22) -> 1 | Q22: 0
A23: 43843 | B23: 0 | C23: 0.7275074 | D23: 0.0321851 | E23: Phase I | F23: =AVERAGE(B23:D23) -> 0.25323083 | G23: =MAX(B23:D23)-MIN(B23:D23) -> 0.7275074 | H23: =IF(AND(E23="Phase I",OR(F23>$E$6,F23<$E$7,G23>$E$8)),1,0) -> 1 | I23: =$H$4 -> 0.6727815 | J23: =$H$6 -> 0.95913723 | K23: =$H$7 -> 0.38642576 | L23: =$H$5 -> 0.27991763 | M23: =$H$8 -> 0.72050798 | N23: =IF(OR(F23>J23,F23<K23),1,0) -> 1 | O23: =IF(G23>M23,1,0) -> 1 | P23: =SIGN(F23-I23) -> -1 | Q23: =IF(ABS(SUM(P16:P23))=8,1,0) -> 0
A24: 43844 | B24: 0.68837075 | C24: 0.84156654 | D24: 0.87574486 | E24: Phase I | F24: =AVERAGE(B24:D24) -> 0.80189405 | G24: =MAX(B24:D24)-MIN(B24:D24) -> 0.18737412 | H24: =IF(AND(E24="Phase I",OR(F24>$E$6,F24<$E$7,G24>$E$8)),1,0) -> 0 | I24: =$H$4 -> 0.6727815 | J24: =$H$6 -> 0.95913723 | K24: =$H$7 -> 0.38642576 | L24: =$H$5 -> 0.27991763 | M24: =$H$8 -> 0.72050798 | N24: =IF(OR(F24>J24,F24<K24),1,0) -> 0 | O24: =IF(G24>M24,1,0) -> 0 | P24: =SIGN(F24-I24) -> 1 | Q24: =IF(ABS(SUM(P17:P24))=8,1,0) -> 0
A25: 43845 | B25: 0.71402428 | C25: 0.74394712 | D25: 0.56405934 | E25: Phase I | F25: =AVERAGE(B25:D25) -> 0.67401025 | G25: =MAX(B25:D25)-MIN(B25:D25) -> 0.17988778 | H25: =IF(AND(E25="Phase I",OR(F25>$E$6,F25<$E$7,G25>$E$8)),1,0) -> 0 | I25: =$H$4 -> 0.6727815 | J25: =$H$6 -> 0.95913723 | K25: =$H$7 -> 0.38642576 | L25: =$H$5 -> 0.27991763 | M25: =$H$8 -> 0.72050798 | N25: =IF(OR(F25>J25,F25<K25),1,0) -> 0 | O25: =IF(G25>M25,1,0) -> 0 | P25: =SIGN(F25-I25) -> 1 | Q25: =IF(ABS(SUM(P18:P25))=8,1,0) -> 0
A26: 43846 | B26: 0.68204246 | C26: 0.76416703 | D26: 0.64566921 | E26: Phase I | F26: =AVERAGE(B26:D26) -> 0.6972929 | G26: =MAX(B26:D26)-MIN(B26:D26) -> 0.11849782 | H26: =IF(AND(E26="Phase I",OR(F26>$E$6,F26<$E$7,G26>$E$8)),1,0) -> 0 | I26: =$H$4 -> 0.6727815 | J26: =$H$6 -> 0.95913723 | K26: =$H$7 -> 0.38642576 | L26: =$H$5 -> 0.27991763 | M26: =$H$8 -> 0.72050798 | N26: =IF(OR(F26>J26,F26<K26),1,0) -> 0 | O26: =IF(G26>M26,1,0) -> 0 | P26: =SIGN(F26-I26) -> 1 | Q26: =IF(ABS(SUM(P19:P26))=8,1,0) -> 0
A27: 43847 | B27: 0.78985488 | C27: 0.76304967 | D27: 0.77832618 | E27: Phase I | F27: =AVERAGE(B27:D27) -> 0.77707691 | G27: =MAX(B27:D27)-MIN(B27:D27) -> 0.026805213 | H27: =IF(AND(E27="Phase I",OR(F27>$E$6,F27<$E$7,G27>$E$8)),1,0) -> 0 | I27: =$H$4 -> 0.6727815 | J27: =$H$6 -> 0.95913723 | K27: =$H$7 -> 0.38642576 | L27: =$H$5 -> 0.27991763 | M27: =$H$8 -> 0.72050798 | N27: =IF(OR(F27>J27,F27<K27),1,0) -> 0 | O27: =IF(G27>M27,1,0) -> 0 | P27: =SIGN(F27-I27) -> 1 | Q27: =IF(ABS(SUM(P20:P27))=8,1,0) -> 0
A28: 43850 | B28: 0 | C28: 0 | D28: 0 | E28: Phase I | F28: =AVERAGE(B28:D28) -> 0 | G28: =MAX(B28:D28)-MIN(B28:D28) -> 0 | H28: =IF(AND(E28="Phase I",OR(F28>$E$6,F28<$E$7,G28>$E$8)),1,0) -> 1 | I28: =$H$4 -> 0.6727815 | J28: =$H$6 -> 0.95913723 | K28: =$H$7 -> 0.38642576 | L28: =$H$5 -> 0.27991763 | M28: =$H$8 -> 0.72050798 | N28: =IF(OR(F28>J28,F28<K28),1,0) -> 1 | O28: =IF(G28>M28,1,0) -> 0 | P28: =SIGN(F28-I28) -> -1 | Q28: =IF(ABS(SUM(P21:P28))=8,1,0) -> 0
A29: 43851 | B29: 0 | C29: 0 | D29: 0.3951653 | E29: Phase I | F29: =AVERAGE(B29:D29) -> 0.13172177 | G29: =MAX(B29:D29)-MIN(B29:D29) -> 0.3951653 | H29: =IF(AND(E29="Phase I",OR(F29>$E$6,F29<$E$7,G29>$E$8)),1,0) -> 1 | I29: =$H$4 -> 0.6727815 | J29: =$H$6 -> 0.95913723 | K29: =$H$7 -> 0.38642576 | L29: =$H$5 -> 0.27991763 | M29: =$H$8 -> 0.72050798 | N29: =IF(OR(F29>J29,F29<K29),1,0) -> 1 | O29: =IF(G29>M29,1,0) -> 0 | P29: =SIGN(F29-I29) -> -1 | Q29: =IF(ABS(SUM(P22:P29))=8,1,0) -> 0
A30: 43852 | B30: 0.73486835 | C30: 0.83501571 | D30: 0.91105729 | E30: Phase I | F30: =AVERAGE(B30:D30) -> 0.82698045 | G30: =MAX(B30:D30)-MIN(B30:D30) -> 0.17618893 | H30: =IF(AND(E30="Phase I",OR(F30>$E$6,F30<$E$7,G30>$E$8)),1,0) -> 0 | I30: =$H$4 -> 0.6727815 | J30: =$H$6 -> 0.95913723 | K30: =$H$7 -> 0.38642576 | L30: =$H$5 -> 0.27991763 | M30: =$H$8 -> 0.72050798 | N30: =IF(OR(F30>J30,F30<K30),1,0) -> 0 | O30: =IF(G30>M30,1,0) -> 0 | P30: =SIGN(F30-I30) -> 1 | Q30: =IF(ABS(SUM(P23:P30))=8,1,0) -> 0
A31: 43853 | B31: 0 | C31: 0.89295379 | D31: 0.58111214 | E31: Phase I | F31: =AVERAGE(B31:D31) -> 0.49135531 | G31: =MAX(B31:D31)-MIN(B31:D31) -> 0.89295379 | H31: =IF(AND(E31="Phase I",OR(F31>$E$6,F31<$E$7,G31>$E$8)),1,0) -> 1 | I31: =$H$4 -> 0.6727815 | J31: =$H$6 -> 0.95913723 | K31: =$H$7 -> 0.38642576 | L31: =$H$5 -> 0.27991763 | M31: =$H$8 -> 0.72050798 | N31: =IF(OR(F31>J31,F31<K31),1,0) -> 0 | O31: =IF(G31>M31,1,0) -> 1 | P31: =SIGN(F31-I31) -> -1 | Q31: =IF(ABS(SUM(P24:P31))=8,1,0) -> 0
A32: 43854 | B32: 0.75578638 | C32: 0.65102328 | D32: 0.84953576 | E32: Phase I | F32: =AVERAGE(B32:D32) -> 0.75211514 | G32: =MAX(B32:D32)-MIN(B32:D32) -> 0.19851248 | H32: =IF(AND(E32="Phase I",OR(F32>$E$6,F32<$E$7,G32>$E$8)),1,0) -> 0 | I32: =$H$4 -> 0.6727815 | J32: =$H$6 -> 0.95913723 | K32: =$H$7 -> 0.38642576 | L32: =$H$5 -> 0.27991763 | M32: =$H$8 -> 0.72050798 | N32: =IF(OR(F32>J32,F32<K32),1,0) -> 0 | O32: =IF(G32>M32,1,0) -> 0 | P32: =SIGN(F32-I32) -> 1 | Q32: =IF(ABS(SUM(P25:P32))=8,1,0) -> 0
A33: 43857 | B33: 0.78156134 | C33: 0.78464159 | D33: 0.59348514 | E33: Phase I | F33: =AVERAGE(B33:D33) -> 0.71989602 | G33: =MAX(B33:D33)-MIN(B33:D33) -> 0.19115645 | H33: =IF(AND(E33="Phase I",OR(F33>$E$6,F33<$E$7,G33>$E$8)),1,0) -> 0 | I33: =$H$4 -> 0.6727815 | J33: =$H$6 -> 0.95913723 | K33: =$H$7 -> 0.38642576 | L33: =$H$5 -> 0.27991763 | M33: =$H$8 -> 0.72050798 | N33: =IF(OR(F33>J33,F33<K33),1,0) -> 0 | O33: =IF(G33>M33,1,0) -> 0 | P33: =SIGN(F33-I33) -> 1 | Q33: =IF(ABS(SUM(P26:P33))=8,1,0) -> 0
A34: 43858 | B34: 0.65524418 | C34: 0.66720299 | D34: 0.66710754 | E34: Phase I | F34: =AVERAGE(B34:D34) -> 0.6631849 | G34: =MAX(B34:D34)-MIN(B34:D34) -> 0.011958811 | H34: =IF(AND(E34="Phase I",OR(F34>$E$6,F34<$E$7,G34>$E$8)),1,0) -> 0 | I34: =$H$4 -> 0.6727815 | J34: =$H$6 -> 0.95913723 | K34: =$H$7 -> 0.38642576 | L34: =$H$5 -> 0.27991763 | M34: =$H$8 -> 0.72050798 | N34: =IF(OR(F34>J34,F34<K34),1,0) -> 0 | O34: =IF(G34>M34,1,0) -> 0 | P34: =SIGN(F34-I34) -> -1 | Q34: =IF(ABS(SUM(P27:P34))=8,1,0) -> 0
... A494: 44560 | B494: 0.67209868 | C494: 0.72675162 | D494: 0.71177801 | E494: Phase II | F494: =AVERAGE(B494:D494) -> 0.70354277 | G494: =MAX(B494:D494)-MIN(B494:D494) -> 0.054652941 | H494: =IF(AND(E494="Phase I",OR(F494>$E$6,F494<$E$7,G494>$E$8)),1,0) -> 0 | I494: =$H$4 -> 0.6727815 | J494: =$H$6 -> 0.95913723 | K494: =$H$7 -> 0.38642576 | L494: =$H$5 -> 0.27991763 | M494: =$H$8 -> 0.72050798 | N494: =IF(OR(F494>J494,F494<K494),1,0) -> 0 | O494: =IF(G494>M494,1,0) -> 0 | P494: =SIGN(F494-I494) -> 1 | Q494: =IF(ABS(SUM(P487:P494))=8,1,0) -> 0

Sheet C2_Capability
A1: C2 - Process capability of s_1 against the OEE target (one-sided, LSL only)
A2: CONTROL. Cpk uses within-subgroup sigma (R-bar/d2); Ppk uses overall sigma. OEE is bounded and skewed - treat indices as indicative.
A5: LSL (OEE target) | B5: =Inputs!$B$5 -> 0.65
A6: Mean of all shift OEE values | B6: =AVERAGE(C1_XbarR_s1!B16:D494) -> 0.62029196
A7: Overall sigma (all shifts) | B7: =STDEV(C1_XbarR_s1!B16:D494) -> 0.23916958
A8: Within sigma = R-bar / d2 | B8: =C1_XbarR_s1!H10 -> 0.16533823
A9: Cpk (lower) | B9: =(B6-B5)/(3*B8) -> -0.05989347
A10: Ppk (lower) | B10: =(B6-B5)/(3*B7) -> -0.041404431
A11: % of shifts below LSL | B11: =COUNTIF(C1_XbarR_s1!B16:D494,"<"&B5)/COUNT(C1_XbarR_s1!B16:D494) -> 0.39874739
A12: % of days (X-bar) below LSL | B12: =COUNTIF(C1_XbarR_s1!F16:F494,"<"&B5)/COUNT(C1_XbarR_s1!F16:F494) -> 0.46137787
A13: Z-bench (overall) | B13: =NORMSINV(1-B11) -> 0.25659067
A14: Verdict | B14: =IF(B10>=1.33,"Capable",IF(B10>=1,"Marginal","NOT capable - centred below target and drifting down in 2021: improve first, then monitor")) -> NOT capable - centred below target and drifting down in 2021: improve first, then monitor

Sheet C3_ControlPlan
A1: C3 - Control plan
A2: CONTROL. Hand this to the process owner at the Control tollgate.
A4: Metric (CTQ) | B4: Spec / target | C4: Measurement (source) | D4: Sample / frequency | E4: Control method | F4: Reaction plan | G4: Owner
A5: Daily OEE, s_1 (shift subgroups) | B5: CL / limits from C1; target >= 65% | C5: v_xbar_r_chart (PostgreSQL) -> Power BI | D5: 3 shifts / day, reviewed daily | E5: X-bar & R chart | F5: OCAP rules 1-3 (C4) | G5: Shift lead
A6: Idle share by shift | B6: <= 20% of planned time | C6: v_shift_state_share | D6: Every shift | E6: Run chart + idle-reason Pareto | F6: Escalate if > 25% two shifts running | G6: Production mgr
A7: % idle minutes with reason code | B7: >= 95% | C7: HMI reason codes (new) | D7: Daily | E7: Poka-Yoke interlock + audit | F7: Fix HMI / retrain | G7: IT + shift lead
A8: A_065 stops per run-hour | B8: -30% vs baseline | C8: v_pareto_alarm_machine | D8: Weekly | E8: Pareto + trend | F8: Re-open Kaizen | G8: Maintenance
A9: Changeover minutes | B9: Target from I3 | C9: v_smed_baseline | D9: Every changeover | E9: SMED standard + timing log | F9: Review with setup tech | G9: Setup lead
A10: Package quality | B10: >= 99.5% | C10: v_daily_machine (po/pi) | D10: Daily | E10: Trend vs LSL | F10: Quality hold if < 99.0% | G10: QA
A11: Material service level / SS | B11: >= 98% CSL | C11: v_inventory_policy | D11: Monthly re-fit | E11: ROP/EOQ refresh + Kanban audit | F11: Re-size SS if demand shifts > 20% | G11: Stores / planning
A12: 5S audit score | B12: >= 80% | C12: I5_5S_Audit | D12: Weekly (pilot), monthly | E12: Audit + actions | F12: Supervisor walk | G12: Area owner

Sheet C4_OCAP
A1: C4 - Out-of-control action plan (OCAP) for the X-bar & R chart
A2: CONTROL.
A4: Signal | B4: Meaning | C4: First response (within the shift) | D4: Escalation
A5: X-bar below LCL (1 point) | B5: A day far worse than normal - special cause | C5: Check idle reasons and top alarms for that day; log the cause | D5: Production mgr same day
A6: X-bar above UCL | B6: Unusually good day | C6: Find out what was different; capture it as standard | D6: CI engineer
A7: R above UCL | B7: One shift much worse than the others | C7: Compare shifts: staffing, material, changeover | D7: Shift leads meeting
A8: 8 X-bar points in a row one side of CL | B8: Sustained shift in the mean | C8: If below: re-open RCA; if above: re-compute limits after 25 subgroups | D8: BB/GB + sponsor
A9: Limits exceed 0-100% | B9: Natural bounds of OEE | C9: Read limits as 0% / 100% | D9: -

Sheet Data_Daily
A1: equipment_id | B1: prod_date | C1: logged_s | D1: scheduled_downtime_s | E1: planned_s | F1: run_s | G1: production_s | H1: performance_loss_s | I1: downtime_s | J1: idle_s | K1: ideal_run_units | L1: units_in | M1: units_out | N1: downtime_rows | O1: year | P1: valid_day (planned>=4h) | Q1: oee_daily | R1: stops_per_run_h
A2: s_1 | B2: 43831 | C2: 67907.517 | D2: 8669.459 | E2: 59238.058 | F2: 48169.553 | G2: 42397.835 | H2: 5771.718 | I2: 7956.862 | J2: 3111.643 | K2: 34361.771 | L2: 35647 | M2: 35449 | N2: 43 | O2: =YEAR(B2) -> 2020 | P2: =IF(AND(E2>=14400,K2>0,L2>0),1,0) -> 1 | Q2: =IF(P2=1,F2/E2*MIN(L2/K2,1)*MIN(MAX(M2/L2,0),1),0) -> 0.8086355 | R2: =IF(F2>0,N2/(F2/3600),0) -> 3.2136483
A3: s_1 | B3: 43832 | C3: 86162.098 | D3: 8016.058 | E3: 78146.04 | F3: 62934.874 | G3: 48460.113 | H3: 14474.761 | I3: 12097.257 | J3: 3113.909 | K3: 52255.679 | L3: 46903 | M3: 46627 | N3: 85 | O3: =YEAR(B3) -> 2020 | P3: =IF(AND(E3>=14400,K3>0,L3>0),1,0) -> 1 | Q3: =IF(P3=1,F3/E3*MIN(L3/K3,1)*MIN(MAX(M3/L3,0),1),0) -> 0.71860192 | R3: =IF(F3>0,N3/(F3/3600),0) -> 4.8621691
A4: s_1 | B4: 43833 | C4: 82386.926 | D4: 7362.958 | E4: 75023.968 | F4: 61655.218 | G4: 49086.719 | H4: 12568.499 | I4: 10712.968 | J4: 2655.782 | K4: 66283.079 | L4: 52163 | M4: 51963 | N4: 78 | O4: =YEAR(B4) -> 2020 | P4: =IF(AND(E4>=14400,K4>0,L4>0),1,0) -> 1 | Q4: =IF(P4=1,F4/E4*MIN(L4/K4,1)*MIN(MAX(M4/L4,0),1),0) -> 0.64426027 | R4: =IF(F4>0,N4/(F4/3600),0) -> 4.554359
A5: s_1 | B5: 43834 | C5: 25415.72 | D5: 5582.28 | E5: 19833.44 | F5: 15456.741 | G5: 14646.769 | H5: 809.972 | I5: 1310.509 | J5: 3066.19 | K5: 19320.926 | L5: 18340 | M5: 18293 | N5: 10 | O5: =YEAR(B5) -> 2020 | P5: =IF(AND(E5>=14400,K5>0,L5>0),1,0) -> 1 | Q5: =IF(P5=1,F5/E5*MIN(L5/K5,1)*MIN(MAX(M5/L5,0),1),0) -> 0.73786494 | R5: =IF(F5>0,N5/(F5/3600),0) -> 2.3290809
A6: s_1 | B6: 43835 | C6: 58239.147 | D6: 3416.9 | E6: 54822.247 | F6: 47207.492 | G6: 38274.067 | H6: 8933.425 | I6: 5181.792 | J6: 2432.963 | K6: 36173.703 | L6: 31613 | M6: 31408 | N6: 29 | O6: =YEAR(B6) -> 2020 | P6: =IF(AND(E6>=14400,K6>0,L6>0),1,0) -> 1 | Q6: =IF(P6=1,F6/E6*MIN(L6/K6,1)*MIN(MAX(M6/L6,0),1),0) -> 0.74765529 | R6: =IF(F6>0,N6/(F6/3600),0) -> 2.2115134
A7: s_1 | B7: 43836 | C7: 86088.328 | D7: 8458.929 | E7: 77629.399 | F7: 70259.159 | G7: 54746.669 | H7: 15512.49 | I7: 4665.739 | J7: 2704.501 | K7: 28878.735 | L7: 28633 | M7: 28489 | N7: 39 | O7: =YEAR(B7) -> 2020 | P7: =IF(AND(E7>=14400,K7>0,L7>0),1,0) -> 1 | Q7: =IF(P7=1,F7/E7*MIN(L7/K7,1)*MIN(MAX(M7/L7,0),1),0) -> 0.89284438 | R7: =IF(F7>0,N7/(F7/3600),0) -> 1.998316
A8: s_1 | B8: 43837 | C8: 82572.118 | D8: 8139.317 | E8: 74432.801 | F8: 68556.59 | G8: 54436.541 | H8: 14120.049 | I8: 3518.649 | J8: 2357.562 | K8: 84249.543 | L8: 65782 | M8: 65552 | N8: 34 | O8: =YEAR(B8) -> 2020 | P8: =IF(AND(E8>=14400,K8>0,L8>0),1,0) -> 1 | Q8: =IF(P8=1,F8/E8*MIN(L8/K8,1)*MIN(MAX(M8/L8,0),1),0) -> 0.71664362 | R8: =IF(F8>0,N8/(F8/3600),0) -> 1.7853864
A9: s_1 | B9: 43838 | C9: 85891.307 | D9: 3396.818 | E9: 82494.489 | F9: 74698.129 | G9: 62210.077 | H9: 12488.052 | I9: 7354.94 | J9: 441.42 | K9: 63552.787 | L9: 54051 | M9: 53783 | N9: 55 | O9: =YEAR(B9) -> 2020 | P9: =IF(AND(E9>=14400,K9>0,L9>0),1,0) -> 1 | Q9: =IF(P9=1,F9/E9*MIN(L9/K9,1)*MIN(MAX(M9/L9,0),1),0) -> 0.76629362 | R9: =IF(F9>0,N9/(F9/3600),0) -> 2.6506688
A10: s_1 | B10: 43839 | C10: 85224.727 | D10: 10182.098 | E10: 75042.629 | F10: 63126.28 | G10: 50783.68 | H10: 12342.6 | I10: 6968.291 | J10: 4948.058 | K10: 49046.034 | L10: 41253 | M10: 40971 | N10: 47 | O10: =YEAR(B10) -> 2020 | P10: =IF(AND(E10>=14400,K10>0,L10>0),1,0) -> 1 | Q10: =IF(P10=1,F10/E10*MIN(L10/K10,1)*MIN(MAX(M10/L10,0),1),0) -> 0.70270788 | R10: =IF(F10>0,N10/(F10/3600),0) -> 2.6803417
A11: s_1 | B11: 43840 | C11: 85147.38 | D11: 7184.638 | E11: 77962.742 | F11: 63786.086 | G11: 55895.504 | H11: 7890.582 | I11: 11470.177 | J11: 2706.479 | K11: 80584.545 | L11: 70715 | M11: 70551 | N11: 68 | O11: =YEAR(B11) -> 2020 | P11: =IF(AND(E11>=14400,K11>0,L11>0),1,0) -> 1 | Q11: =IF(P11=1,F11/E11*MIN(L11/K11,1)*MIN(MAX(M11/L11,0),1),0) -> 0.71629227 | R11: =IF(F11>0,N11/(F11/3600),0) -> 3.8378276
A12: s_1 | B12: 43841 | C12: 23148.88 | D12: 5660.24 | E12: 17488.64 | F12: 13282.39 | G12: 10732.66 | H12: 2549.73 | I12: 1333.13 | J12: 2873.12 | K12: 16602.987 | L12: 13423 | M12: 13399 | N12: 11 | O12: =YEAR(B12) -> 2020 | P12: =IF(AND(E12>=14400,K12>0,L12>0),1,0) -> 1 | Q12: =IF(P12=1,F12/E12*MIN(L12/K12,1)*MIN(MAX(M12/L12,0),1),0) -> 0.61292359 | R12: =IF(F12>0,N12/(F12/3600),0) -> 2.9813912
A13: s_1 | B13: 43842 | C13: 81649.76 | D13: 21089.571 | E13: 60560.189 | F13: 19313.038 | G13: 14631.368 | H13: 4681.67 | I13: 7918.622 | J13: 33328.529 | K13: 0 | L13: 1991 | M13: 1950 | N13: 14 | O13: =YEAR(B13) -> 2020 | P13: =IF(AND(E13>=14400,K13>0,L13>0),1,0) -> 0 | Q13: =IF(P13=1,F13/E13*MIN(L13/K13,1)*MIN(MAX(M13/L13,0),1),0) -> 0 | R13: =IF(F13>0,N13/(F13/3600),0) -> 2.609636
... A2407: s_5 | B2407: 44562 | C2407: 56333.482 | D2407: 9124.898 | E2407: 47208.584 | F2407: 31537.251 | G2407: 30028.087 | H2407: 1509.164 | I2407: 739.608 | J2407: 14931.725 | K2407: 55102.505 | L2407: 51380 | M2407: 51326 | N2407: 6 | O2407: =YEAR(B2407) -> 2022 | P2407: =IF(AND(E2407>=14400,K2407>0,L2407>0),1,0) -> 1 | Q2407: =IF(P2407=1,F2407/E2407*MIN(L2407/K2407,1)*MIN(MAX(M2407/L2407,0),1),0) -> 0.62225578 | R2407: =IF(F2407>0,N2407/(F2407/3600),0) -> 0.68490434

Sheet Data_Shift
A1: equipment_id | B1: prod_date | C1: shift | D1: idle_share | E1: downtime_share | F1: is_weekend | G1: year
A2: s_1 | B2: 43831 | C2: B | D2: 0.0050701173 | E2: 0.096929798 | F2: 0 | G2: 2020
A3: s_1 | B3: 43831 | C3: C | D3: 0 | E3: 0.18807407 | F3: 0 | G3: 2020
A4: s_1 | B4: 43832 | C4: A | D4: 0.025737723 | E4: 0.28749365 | F4: 0 | G4: 2020
A5: s_1 | B5: 43832 | C5: B | D5: 0.051073714 | E5: 0.12080616 | F5: 0 | G5: 2020
A6: s_1 | B6: 43832 | C6: C | D6: 0.043833825 | E6: 0.044584123 | F6: 0 | G6: 2020
A7: s_1 | B7: 43833 | C7: A | D7: 0 | E7: 0.31623847 | F7: 0 | G7: 2020
A8: s_1 | B8: 43833 | C8: B | D8: 0.0080386071 | E8: 0.038479938 | F8: 0 | G8: 2020
A9: s_1 | B9: 43833 | C9: C | D9: 0.14013128 | E9: 0.046056914 | F9: 0 | G9: 2020
A10: s_1 | B10: 43834 | C10: A | D10: 0.15459698 | E10: 0.066075729 | F10: 1 | G10: 2020
A11: s_1 | B11: 43835 | C11: B | D11: 0.00062765215 | E11: 0.096361254 | F11: 1 | G11: 2020
A12: s_1 | B12: 43835 | C12: C | D12: 0.0080118186 | E12: 0.10237769 | F12: 1 | G12: 2020
A13: s_1 | B13: 43836 | C13: A | D13: 0.012273125 | E13: 0.074343291 | F13: 0 | G13: 2020
... A5993: s_5 | B5993: 44562 | C5993: B | D5993: 0.85526763 | E5993: 0 | F5993: 1 | G5993: 2022
